Workbook

Sheet Spend Export
A1: Business Partner Company Name | B1: Branch Id | C1: Main Category | D1: Sub Category | E1: Spend | F1: E-invoicing | G1: PO coverage | H1: Spend Under Control Coverage | I1: Count of Invoice Receipts | J1: Actual Invoice Payment Time Average (Invoice amount weighted) | K1: Invoice Payment Period Average (Invoice amount weighted) | L1: Business Partner Payment Terms Id | M1: SSC Policy Signed | N1: Supplier Missing Data
A2: Presto Oy | B2: 607555 | C2: IPPE - Personnel | D2: IPPE06 - Training & people development | E2: 37788.89 | I2: 67 | J2: 23.575455 | K2: 15.980053 | L2: STOP_N45 | M2: Yes | N2: No
A3: Edward Lynx AB | B3: 404521 | C3: IPPE - Personnel | D3: IPPE06 - Training & people development | E3: 692085 | I3: 44 | J3: 77.293244 | K3: 57.992502 | L3: STOP_N60 | M3: Yes | N3: No
A4: Hope Consulting Oy | B4: 389324 | C4: IPPE - Personnel | D4: IPPE06 - Training & people development | E4: 38500 | I4: 43 | J4: 29.890909 | K4: 14 | L4: STOP_N60 | M4: Yes | N4: No
A5: Sähköinfo Oy | B5: 604917 | C5: IPPE - Personnel | D5: IPPE06 - Training & people development | E5: 24830.14 | G5: 0.025 | H5: 0.042287317 | I5: 40 | J5: 24.526368 | K5: 17.103567 | L5: STOP_N45 | M5: No | N5: No
A6: Suomen Ensiapukoulutus Oy | B6: 332750 | C6: IPPE - Personnel | D6: IPPE06 - Training & people development | E6: 6838.19 | I6: 39 | J6: 29.872836 | K6: 25.732555 | L6: STOP_N14 | M6: No | N6: No
A7: AEL-Amiedu Oy | B7: 634973 | C7: IPPE - Personnel | D7: IPPE06 - Training & people development | E7: 53171.15 | I7: 24 | J7: 57.415873 | K7: 55.768382 | L7: STOP_N45 | M7: No | N7: No
A8: Apprix Oy | B8: 239755 | C8: IPPE - Personnel | D8: IPPE06 - Training & people development | E8: 16135 | I8: 20 | J8: 45.560378 | K8: 45 | L8: STOP_N45 | M8: No | N8: Yes
A9: Psykologipalvelut Hippu Pintilä | B9: 635240 | C9: IPPE - Personnel | D9: IPPE06 - Training & people development | E9: 26682.13 | I9: 19 | J9: 59.468497 | K9: 60 | L9: STOP_N60 | M9: Yes | N9: No
A10: Resilio Oy | B10: 407540 | C10: IPPE - Personnel | D10: IPPE06 - Training & people development | E10: 56523.34 | I10: 15 | J10: 24.355071 | K10: 3.9275811 | L10: STOP_N45 | M10: Yes | N10: Yes
A11: Jyväskylän Ammattikorkeakoulu | B11: 201515 | C11: IPPE - Personnel | D11: IPPE06 - Training & people development | E11: 53685.65 | G11: 0.071428571 | H11: 0.023986857 | I11: 14 | J11: 45.38641 | K11: 35.14694 | L11: STOP_N30 | M11: No | N11: Yes
A12: Sinkkonen Consulting Oy | B12: 349102 | C12: IPPE - Personnel | D12: IPPE06 - Training & people development | E12: 37360 | I12: 14 | J12: 25.55166 | K12: 24.273822 | L12: STOP_N45 | M12: No | N12: Yes
A13: Abitata | B13: 382766 | C13: IPPE - Personnel | D13: IPPE06 - Training & people development | E13: 10751.26 | I13: 13 | J13: 68.164944 | K13: 29.732124 | L13: STOP_N30 | M13: Yes | N13: Yes
A14: Bitville Oy | B14: 400676 | C14: IPPE - Personnel | D14: IPPE06 - Training & people development | E14: 58512 | I14: 13 | J14: 135.53199 | K14: 165.73175 | L14: STOP_N60 | M14: Yes | N14: No
A15: Finn-Tarkastus Oy | B15: 639705 | C15: IPPE - Personnel | D15: IPPE06 - Training & people development | E15: 19549.56 | G15: 0.15384615 | H15: 0.40561527 | I15: 13 | J15: 50.451247 | K15: 53.915771 | L15: STOP_N45 | M15: No | N15: No
A16: Helsingin Kamari Oy | B16: 509013 | C16: IPPE - Personnel | D16: IPPE06 - Training & people development | E16: 31866 | I16: 13 | J16: 39.680262 | K16: 25.155353 | L16: STOP_N45 | M16: No | N16: Yes
A17: IMD-International Institute for Managem. Develop. | B17: 383390 | C17: IPPE - Personnel | D17: IPPE06 - Training & people development | E17: 1524625.8 | I17: 13 | J17: 62.971378 | K17: 60 | L17: STOP_N60 | M17: No | N17: Yes
A18: Soutwestern Consulting LTD | B18: 656486 | C18: IPPE - Personnel | D18: IPPE06 - Training & people development | E18: 7325 | I18: 12 | J18: 19.112628 | K18: 17.767918 | L18: STOP_N60 | M18: Yes | N18: No
A19: Aalto University Executive Education Oy | B19: 615149 | C19: IPPE - Personnel | D19: IPPE06 - Training & people development | E19: 220586.65 | I19: 11 | J19: 42.552561 | K19: 40.944002 | L19: STOP_N45 | M19: Yes | N19: No
A20: Punainen Risti Ensiapu Oy | B20: 408310 | C20: IPPE - Personnel | D20: IPPE06 - Training & people development | E20: 2361 | I20: 11 | J20: 26.824227 | K20: 29.35197 | L20: STOP_N14 | M20: No | N20: Yes
A21: Tulityö ja työturvallisuuskoulutus Kalle Hankomäki Oy | B21: 380921 | C21: IPPE - Personnel | D21: IPPE06 - Training & people development | E21: 1401.9 | I21: 11 | J21: 29.726799 | K21: 14 | L21: STOP_N45 | M21: No | N21: Yes
A22: AS3 Finland Oy | B22: 403389 | C22: IPPE - Personnel | D22: IPPE06 - Training & people development | E22: 28297.19 | I22: 10 | J22: 56.38003 | K22: 52.759062 | L22: STOP_N60 | M22: Yes | N22: No
A23: Koolituskorraldus OÜ | B23: 641406 | C23: IPPE - Personnel | D23: IPPE06 - Training & people development | E23: 1791.99 | I23: 10 | J23: 19.333272 | K23: 7.9285654 | L23: STOP_N14 | M23: Yes | N23: No
A24: Hyvinvoinnin Suurlähettiläät Oy | B24: 635292 | C24: IPPE - Personnel | D24: IPPE06 - Training & people development | E24: 48739.9 | G24: 0.77777778 | H24: 0.71891612 | I24: 9 | J24: 64.68351 | K24: 49.938531 | L24: STOP_N60 | M24: No | N24: Yes
A25: BCFO Business Coaching Finland Oy | B25: 374821 | C25: IPPE - Personnel | D25: IPPE06 - Training & people development | E25: 52639 | I25: 8 | J25: 24.175706 | K25: 11.8723 | L25: STOP_N45 | M25: No | N25: Yes
A26: Oy Speakers Forum Finland Ab | B26: 331659 | C26: IPPE - Personnel | D26: IPPE06 - Training & people development | E26: 11146 | I26: 8 | J26: 27.523955 | K26: 22.182487 | L26: STOP_N45 | M26: No | N26: Yes
A27: Pohto Oy | B27: 602473 | C27: IPPE - Personnel | D27: IPPE06 - Training & people development | E27: 11712.9 | I27: 8 | J27: 42.462127 | K27: 43.351689 | L27: STOP_N45 | M27: No | N27: Yes
A28: Imaction | B28: 646544 | C28: IPPE - Personnel | D28: IPPE06 - Training & people development | E28: 39100 | I28: 7 | J28: 60.768542 | K28: 61.276215 | L28: STOP_N60 | M28: Yes | N28: No
A29: Presto Oy | B29: 511007 | C29: IPPE - Personnel | D29: IPPE06 - Training & people development | E29: 3927.33 | I29: 7 | J29: 22.392893 | K29: 14 | L29: STOP_N45 | M29: Yes | N29: No
A30: Rokmind Oy | B30: 647801 | C30: IPPE - Personnel | D30: IPPE06 - Training & people development | E30: 7000 | I30: 7 | J30: 60.46 | K30: 60 | L30: STOP_N60 | M30: Yes | N30: No
A31: Tampere Business Campus TBC ry | B31: 224445 | C31: IPPE - Personnel | D31: IPPE06 - Training & people development | E31: 21295 | I31: 7 | J31: 32.705095 | K31: 30 | L31: STOP_N30 | M31: No | N31: No
A32: EF Language Learning Solutions AG | B32: 310141 | C32: IPPE - Personnel | D32: IPPE06 - Training & people development | E32: 4947.42 | I32: 6 | J32: 151.60276 | K32: 60 | L32: STOP_N60 | M32: Yes | N32: No
A33: International Institute for Learning Finland Oy | B33: 295648 | C33: IPPE - Personnel | D33: IPPE06 - Training & people development | E33: 31615.03 | I33: 6 | J33: 63.156131 | K33: 60.734212 | L33: STOP_N60 | M33: No | N33: No
A34: Peili Consulting Oy | B34: 386353 | C34: IPPE - Personnel | D34: IPPE06 - Training & people development | E34: 17679.65 | I34: 6 | J34: 61.62838 | K34: 60 | L34: STOP_N60 | M34: Yes | N34: No
A35: HAK Nova Oy | B35: 630977 | C35: IPPE - Personnel | D35: IPPE06 - Training & people development | E35: 4980 | I35: 5 | J35: 34.620482 | K35: 36.174699 | L35: STOP_N60 | M35: Yes | N35: No
A36: Innotiimi Oy | B36: 604023 | C36: IPPE - Personnel | D36: IPPE06 - Training & people development | E36: 45434.45 | I36: 5 | J36: 56.610278 | K36: 56.877998 | L36: STOP_N45 | M36: Yes | N36: Yes
A37: Kajaanin Ammattikorkeakoulu Oy | B37: 386089 | C37: IPPE - Personnel | D37: IPPE06 - Training & people development | E37: 10447.8 | G37: 0.8 | H37: 0.78942935 | I37: 5 | J37: 50.351021 | K37: 51.135502 | L37: STOP_N45 | M37: Yes | N37: No
A38: Tina Sammi Oy | B38: 633539 | C38: IPPE - Personnel | D38: IPPE06 - Training & people development | E38: 3050 | I38: 5 | J38: 26.880952 | K38: 17.619048 | L38: STOP_N14 | M38: No | N38: No
A39: Catling Oy | B39: 663141 | C39: IPPE - Personnel | D39: IPPE06 - Training & people development | E39: 10000 | I39: 4 | J39: 39.9 | K39: 14 | L39: STOP_N30 | M39: Yes | N39: No
A40: Elina Lillstrang Oy | B40: 637008 | C40: IPPE - Personnel | D40: IPPE06 - Training & people development | E40: 22243.72 | I40: 4 | J40: 19.073375 | K40: 14 | L40: STOP_N60 | M40: Yes | N40: No
A41: IMPLEMENT CONSULTING GROUP P/S | B41: 391772 | C41: IPPE - Personnel | D41: IPPE06 - Training & people development | E41: 120751.04 | I41: 4 | J41: 60.327226 | K41: 60 | L41: STOP_N60 | M41: Yes | N41: No
A42: Laatukeskus Excellence Finland Oy | B42: 163473 | C42: IPPE - Personnel | D42: IPPE06 - Training & people development | E42: 12199.2 | I42: 4 | J42: 92.589022 | K42: 80.971605 | L42: STOP_N14 | M42: No | N42: Yes
A43: Logistiikka Koulutus V & P Ky | B43: 304456 | C43: IPPE - Personnel | D43: IPPE06 - Training & people development | E43: 450 | I43: 4 | J43: 16.111111 | K43: 14.666667 | L43: STOP_N60 | M43: Yes | N43: Yes
A44: Professio Group Oy | B44: 356012 | C44: IPPE - Personnel | D44: IPPE06 - Training & people development | E44: 6952 | I44: 4 | J44: 19.459868 | K44: 14 | L44: STOP_N60 | M44: Yes | N44: No
A45: Työturvallisuuskeskus ry | B45: 603082 | C45: IPPE - Personnel | D45: IPPE06 - Training & people development | E45: 978.04 | I45: 4 | J45: 41.986545 | K45: 14 | L45: STOP_N90 | M45: No | N45: No
A46: Ukkonen Palvelut Oy | B46: 628955 | C46: IPPE - Personnel | D46: IPPE06 - Training & people development | E46: 850 | I46: 4 | J46: 18.411765 | K46: 14 | L46: STOP_N60 | M46: Yes | N46: No
A47: Board of Innovation BVBA | B47: 406951 | C47: IPPE - Personnel | D47: IPPE06 - Training & people development | E47: 135525.68 | I47: 3 | J47: 45.122317 | K47: 44.800965 | L47: STOP_N45 | M47: No | N47: Yes
A48: T:mi Kärppä Antti | B48: 301748 | C48: IPPE - Personnel | D48: IPPE06 - Training & people development | E48: 525 | I48: 3 | J48: 21.6 | K48: 14.8 | L48: STOP_N45 | M48: No | N48: Yes
A49: UTK-YHTIÖT OY | B49: 404140 | C49: IPPE - Personnel | D49: IPPE06 - Training & people development | E49: 300 | I49: 3 | J49: 21.5 | K49: 10 | L49: STOP_N60 | M49: Yes | N49: No
... A92: Ratekoulutus Oy | B92: 351748 | C92: IPPE - Personnel | D92: IPPE06 - Training & people development | E92: 397 | I92: 1 | J92: 21 | K92: 21 | L92: STOP_N45 | M92: No | N92: Yes
A93: Risknowlogy GmbH | B93: 304654 | C93: IPPE - Personnel | D93: IPPE06 - Training & people development | E93: 3741 | G93: 1 | H93: 1 | I93: 1 | J93: 47 | K93: 45 | L93: STOP_N45 | M93: Yes | N93: No
A94: RoHS Management Oy | B94: 661653 | C94: IPPE - Personnel | D94: IPPE06 - Training & people development | E94: 6845 | I94: 1 | J94: 34 | K94: 30 | L94: STOP_N60 | M94: Yes | N94: No
A95: Safeguard Engineering Oy | B95: 656961 | C95: IPPE - Personnel | D95: IPPE06 - Training & people development | E95: 2310 | I95: 1 | J95: 55 | K95: 30 | L95: STOP_N30 | M95: Yes | N95: No
A96: Safety First | B96: 663583 | C96: IPPE - Personnel | D96: IPPE06 - Training & people development | E96: 196 | I96: 1 | J96: 41 | K96: 14 | L96: STOP_N60 | M96: Yes | N96: No
A97: Satakunnan Monikulttuuriyhdistys ry | B97: 646402 | C97: IPPE - Personnel | D97: IPPE06 - Training & people development | E97: 8421.5 | I97: 1 | J97: 19 | K97: 21 | L97: STOP_N45 | M97: Yes | N97: No
A98: Sec And Safe Solutions Oy | B98: 668449 | C98: IPPE - Personnel | D98: IPPE06 - Training & people development | E98: 69 | I98: 1 | J98: 35 | K98: 7 | L98: STOP_N60 | M98: Yes | N98: No
A99: Sepon Konttori | B99: 384798 | C99: IPPE - Personnel | D99: IPPE06 - Training & people development | E99: 2905 | I99: 1 | J99: 14 | K99: 14 | L99: STOP_N45 | M99: No | N99: Yes
A100: Suomen Punainen Risti Varsinais-Suomen piiri | B100: 612001 | C100: IPPE - Personnel | D100: IPPE06 - Training & people development | E100: 300 | I100: 1 | J100: 107 | K100: 14 | L100: STOP_N14 | M100: Yes | N100: Yes
A101: Tampereen Sammutin osakeyhtiö | B101: 637584 | C101: IPPE - Personnel | D101: IPPE06 - Training & people development | E101: 1881.9 | I101: 1 | J101: 33 | K101: 30 | L101: STOP_N07 | M101: No | N101: No
A102: TES-toimi Oy | B102: 380922 | C102: IPPE - Personnel | D102: IPPE06 - Training & people development | E102: 120 | I102: 1 | J102: 28 | K102: 14 | L102: STOP_N30 | M102: No | N102: Yes
A103: The European Institute of Purchasing Management | B103: 239503 | C103: IPPE - Personnel | D103: IPPE06 - Training & people development | E103: 3000 | I103: 1 | J103: 29 | K103: 30 | L103: STOP_N45 | M103: Yes | N103: No
A104: Tietojärjestelmien Tarkastus Ja Valvonta Ry | B104: 168488 | C104: IPPE - Personnel | D104: IPPE06 - Training & people development | E104: 1290 | I104: 1 | J104: 19 | K104: 10 | L104: STOP_N10 | M104: Yes | N104: Yes
A105: TJO ry/Helsingin aikuisopisto | B105: 667900 | C105: IPPE - Personnel | D105: IPPE06 - Training & people development | E105: 265 | I105: 1 | J105: 42 | K105: 14 | L105: STOP_N60 | M105: Yes | N105: No
... A110: Biisoni Oy | B110: 344325 | C110: IPPE - Personnel | D110: IPPE07 - Leased workforce | E110: 1459890.1 | I110: 268 | J110: 60.022638 | K110: 60 | L110: STOP_N60 | M110: Yes | N110: No
A111: Adecco Finland Oy | B111: 278118 | C111: IPPE - Personnel | D111: IPPE07 - Leased workforce | E111: 1271566.2 | G111: 0.45794393 | H111: 0.45299516 | I111: 214 | J111: 67.329648 | K111: 56.275664 | L111: STOP_N60 | M111: Yes | N111: No
A112: ManpowerGroup Oy | B112: 607060 | C112: IPPE - Personnel | D112: IPPE07 - Leased workforce | E112: 738534.05 | G112: 0.18079096 | H112: 0.32319261 | I112: 177 | J112: 52.812348 | K112: 48.62023 | L112: STOP_N60 | M112: Yes | N112: No
A113: GoMetan III Oy | B113: 632993 | C113: IPPE - Personnel | D113: IPPE07 - Leased workforce | E113: 786589.18 | I113: 106 | J113: 61.232828 | K113: 60.377981 | L113: STOP_N60 | M113: Yes | N113: No
A114: Rekrytointipalvelu Sihti Oy | B114: 386990 | C114: IPPE - Personnel | D114: IPPE07 - Leased workforce | E114: 453472.05 | I114: 97 | J114: 61.84757 | K114: 60 | L114: STOP_N60 | M114: Yes | N114: No
A115: Biisoni Tampere Oy | B115: 623840 | C115: IPPE - Personnel | D115: IPPE07 - Leased workforce | E115: 949359.13 | G115: 0.36781609 | H115: 0.61276709 | I115: 87 | J115: 60.482105 | K115: 60 | L115: STOP_N60 | M115: Yes | N115: No
A116: Kassavirtanen Oy | B116: 654756 | C116: IPPE - Personnel | D116: IPPE07 - Leased workforce | E116: 79798.61 | I116: 55 | J116: 20.576956 | K116: 19.310671 | L116: STOP_N14 | M116: Yes | N116: No
A117: Ekonomigruppen 3F AB | B117: 511174 | C117: IPPE - Personnel | D117: IPPE07 - Leased workforce | E117: 53669.86 | I117: 16 | J117: 57.28133 | K117: 45 | L117: STOP_N45 | M117: Yes | N117: No
A118: Advantus UAB | B118: 624372 | C118: IPPE - Personnel | D118: IPPE07 - Leased workforce | E118: 57331.27 | I118: 12 | J118: 22.051878 | K118: 10 | L118: STOP_N21 | M118: Yes | N118: No
A119: Wellpack Oy | B119: 662770 | C119: IPPE - Personnel | D119: IPPE07 - Leased workforce | E119: 48516.4 | I119: 11 | J119: 28.145584 | K119: 27.959453 | L119: STOP_N30 | M119: Yes | N119: No
A120: Poolia Sverige Ab | B120: 273437 | C120: IPPE - Personnel | D120: IPPE07 - Leased workforce | E120: 18520.42 | I120: 9 | J120: 60.642191 | K120: 60 | L120: STOP_N60 | M120: Yes | N120: No
A121: StaffPoint Oy | B121: 655274 | C121: IPPE - Personnel | D121: IPPE07 - Leased workforce | E121: 35118.67 | I121: 8 | J121: 32.107038 | K121: 29.97522 | L121: STOP_N60 | M121: Yes | N121: No
A122: Academic Work HR Services Oy | B122: 398910 | C122: IPPE - Personnel | D122: IPPE07 - Leased workforce | E122: 8737.78 | I122: 6 | J122: 63.673391 | K122: 60 | L122: STOP_N45 | M122: Yes | N122: No
A123: Goltens Rotterdam B.V. | B123: 637684 | C123: IPPE - Personnel | D123: IPPE07 - Leased workforce | E123: 42608.74 | I123: 3 | J123: 58 | K123: 30 | L123: STOP_N30 | M123: Yes | N123: No
A124: Kiwa Impact Oy | B124: 284620 | C124: IPPS - Professional services | D124: IPPS01 - Testing, measurement & inspection | E124: 345458.51 | I124: 529 | J124: 50.700572 | K124: 43.613413 | L124: STOP_N60 | M124: Yes | N124: No
A125: DEKRA Industrial Oy | B125: 504367 | C125: IPPS - Professional services | D125: IPPS01 - Testing, measurement & inspection | E125: 806993.13 | G125: 0.53030303 | H125: 0.77525391 | I125: 132 | J125: 58.386732 | K125: 46.419895 | L125: STOP_N45 | M125: Yes | N125: No
A126: Metlab Oy | B126: 501971 | C126: IPPS - Professional services | D126: IPPS01 - Testing, measurement & inspection | E126: 265108.85 | G126: 0.49180328 | H126: 0.70796429 | I126: 122 | J126: 60.111796 | K126: 51.484825 | L126: STOP_N45 | M126: Yes | N126: No
A127: Kiwa Oy | B127: 503357 | C127: IPPS - Professional services | D127: IPPS01 - Testing, measurement & inspection | E127: 436221.64 | G127: 0.28571429 | H127: 0.24417051 | I127: 77 | J127: 56.865734 | K127: 55.948794 | L127: STOP_N30 | M127: Yes | N127: No
A128: Ramboll Finland Oy | B128: 614872 | C128: IPPS - Professional services | D128: IPPS01 - Testing, measurement & inspection | E128: 401487.95 | G128: 0.49056604 | H128: 0.6965028 | I128: 53 | J128: 46.790657 | K128: 40.728811 | L128: STOP_N45 | M128: Yes | N128: No
A129: Säteilyturvakeskus | B129: 603856 | C129: IPPS - Professional services | D129: IPPS01 - Testing, measurement & inspection | E129: 17617.78 | G129: 0.021276596 | H129: 0.005676084 | I129: 47 | J129: 24.806857 | K129: 20.660403 | L129: STOP_N45 | M129: No | N129: No
A130: Eurofins Environment Testing Finland Oy | B130: 406497 | C130: IPPS - Professional services | D130: IPPS01 - Testing, measurement & inspection | E130: 79767.59 | G130: 0.043478261 | H130: 0.036507308 | I130: 46 | J130: 44.986503 | K130: 31.433156 | L130: STOP_N60 | M130: Yes | N130: No
A131: Isq Instituto de Soldadura | B131: 258409 | C131: IPPS - Professional services | D131: IPPS01 - Testing, measurement & inspection | E131: 319294.6 | G131: 1 | H131: 1 | I131: 28 | J131: 46.611808 | K131: 45 | L131: STOP_N45 | M131: No | N131: Yes
A132: Oy Keskuslaboratorio - Centrallaboratorium Ab | B132: 658226 | C132: IPPS - Professional services | D132: IPPS01 - Testing, measurement & inspection | E132: 126157 | G132: 0.52173913 | H132: 0.36150986 | I132: 23 | J132: 48.342224 | K132: 35.422648 | L132: STOP_N45 | M132: Yes | N132: No
A133: Tumedei Spa A Socio Unico | B133: 652119 | C133: IPPS - Professional services | D133: IPPS01 - Testing, measurement & inspection | E133: 95851.56 | G133: 0.88235294 | H133: 0.91124046 | I133: 17 | J133: 79.177214 | K133: 60 | L133: STOP_N60 | M133: Yes | N133: No
A134: Eurofins Expert Services Oy | B134: 649925 | C134: IPPS - Professional services | D134: IPPS01 - Testing, measurement & inspection | E134: 22263 | G134: 0.53846154 | H134: 0.17104613 | I134: 13 | J134: 50.148992 | K134: 33.72187 | L134: STOP_N60 | M134: Yes | N134: No
A135: Hopeajalka Oy | B135: 631702 | C135: IPPS - Professional services | D135: IPPS01 - Testing, measurement & inspection | E135: 106488 | I135: 13 | J135: 30.671024 | K135: 30.232843 | L135: STOP_N30 | M135: Yes | N135: No
A136: Insinööriavain Oy | B136: 651434 | C136: IPPS - Professional services | D136: IPPS01 - Testing, measurement & inspection | E136: 100606.8 | G136: 1 | H136: 1 | I136: 12 | J136: 73.658699 | K136: 60 | L136: STOP_N60 | M136: Yes | N136: No
A137: ALFA INSPEKT D.O.O. | B137: 633450 | C137: IPPS - Professional services | D137: IPPS01 - Testing, measurement & inspection | E137: 88078.52 | G137: 1 | H137: 1 | I137: 9 | J137: 46.022919 | K137: 45 | L137: STOP_N14 | M137: Yes | N137: Yes
A138: Kiwa Impact Oy | B138: 635601 | C138: IPPS - Professional services | D138: IPPS01 - Testing, measurement & inspection | E138: 4074.02 | I138: 9 | J138: 44.660154 | K138: 44.474966 | L138: STOP_N60 | M138: Yes | N138: No
A139: RISE Research Institutes of Sweden AB | B139: 360948 | C139: IPPS - Professional services | D139: IPPS01 - Testing, measurement & inspection | E139: 93432.15 | G139: 0.22222222 | H139: 0.72951655 | I139: 9 | J139: 40.001102 | K139: 30 | L139: STOP_N30 | M139: Yes | N139: No
A140: Mitta Oy | B140: 618729 | C140: IPPS - Professional services | D140: IPPS01 - Testing, measurement & inspection | E140: 14281.4 | G140: 0.125 | H140: 0.12498775 | I140: 8 | J140: 81.706574 | K140: 62.085826 | L140: STOP_N60 | M140: Yes | N140: Yes
A141: Sasu Horiba France SAS | B141: 226316 | C141: IPPS - Professional services | D141: IPPS01 - Testing, measurement & inspection | E141: 161815 | G141: 1 | H141: 1 | I141: 8 | J141: 39.621871 | K141: 30 | L141: STOP_N45 | M141: Yes | N141: No
A142: Solver Oy | B142: 267726 | C142: IPPS - Professional services | D142: IPPS01 - Testing, measurement & inspection | E142: 107457.84 | G142: 0.85714286 | H142: 0.7844711 | I142: 7 | J142: 35.751391 | K142: 33.822546 | L142: STOP_N45 | M142: Yes | N142: No
A143: TÜV AUSTRIA GMBH | B143: 262052 | C143: IPPS - Professional services | D143: IPPS01 - Testing, measurement & inspection | E143: 139474.56 | G143: 1 | H143: 1 | I143: 7 | J143: 62.977569 | K143: 60 | L143: STOP_N30 | M143: Yes | N143: No
A144: CRS Laboratories Oy | B144: 236728 | C144: IPPS - Professional services | D144: IPPS01 - Testing, measurement & inspection | E144: 3242 | I144: 6 | J144: 39.383097 | K144: 30 | L144: STOP_N30 | M144: Yes | N144: No
A145: Kiwa Sweden AB | B145: 508634 | C145: IPPS - Professional services | D145: IPPS01 - Testing, measurement & inspection | E145: 9647.42 | G145: 0.5 | H145: 0.3524901 | I145: 6 | J145: 65.714419 | K145: 42.850959 | L145: STOP_N60 | M145: Yes | N145: No
A146: Eurofins Scientific Finland Oy | B146: 281113 | C146: IPPS - Professional services | D146: IPPS01 - Testing, measurement & inspection | E146: 618.75 | I146: 5 | J146: 46.444444 | K146: 17.555556 | L146: STOP_N30 | M146: Yes | N146: No
...

Sheet Supplierdata with FI spend
A1: Corporation | B1: Company | C1: Branch | D1: City (Street Address) | E1: Country/Region (Street Address) | F1: e-Mail | G1: Supplier Status | H1: Corporation Category | I1: Created | J1: Created By | K1: Company ID | L1: DUNS Code | M1: ValmetID | N1: Finland spend? | O1: Own ID | P1: Company VAT number | Q1: Preferred Supplier | R1: Purchase orders last three years | S1: Invoices last three years | T1: Supplier Categories | U1: Supplier Main Category | V1: Supplier Main Contact | W1: Supplier Main Contact eMail | X1: Terms Of Payment | Y1: Valmet Supplier Code of Conduct signed | Z1: Supplier sustainability policy signed | AA1: Valmet Supplier Manager | AB1: PAP Supplier Manager | AC1: P&E Supplier Manager | AD1: SER Supplier Manager | AE1: AS Supplier Manager | AF1: FC Supplier Manager | AG1: Buyer | AH1: Category Manager | AI1: Latest Approval | AJ1: Is supplier engaged to Valmet climate program? | AK1: MillID
A2: Capgemini Group | B2: Capgemini Finland Oy | C2: Capgemini Finland Oy | D2: HELSINKI | E2: Finland | G2: Active | H2: C3 | I2: 43489.408 | J2: Järvenpää Anssi | K2: 289334 | M2: 628390 | N2: =VLOOKUP(M2,'Spend Export'!$B:$E,4,FALSE) -> #N/A | P2: FI16281425 | Q2: X | R2: Yes | S2: Yes | T2: Indirect procurement iPRO, Office IT, Application management, IT consulting;Indirect procurement iPRO, Office IT, Application management, IT consulting, Other IT | U2: Indirect procurement iPRO, Office IT, Application management, IT consulting | V2: Aripirala Srikanth | W2: aripirala.srikanth@capgemini.com | X2: Net 45 days | Z2: X | AA2: Liukkonen Marko;Tapiola Mika;INACTIVE Länsimies Jukka;Jurvanen Juho | AI2: 2023-06-28 1001 - Infor LN (COF) (Valmet), Indirect procurement iPRO, Office IT, Application management, IT consulting (Main category) accepted by Tapiola Mika | AK2: 628390
A3: Know IT | B3: KnowIt Solutions Oy | C3: KnowIt Solutions Oy | D3: TAMPERE | E3: Finland | G3: Active | H3: C3 | I3: 44509.531 | J3: INACTIVE Kauppinen Ville | K3: 302922 | M3: 646437 | N3: =VLOOKUP(M3,'Spend Export'!$B:$E,4,FALSE) -> #N/A | P3: FI30945961 | R3: Yes | S3: Yes | T3: Indirect procurement iPRO, Office IT, Application management, IT consulting;Services, ICT engineering, ICT engineering | U3: Indirect procurement iPRO, Office IT, Application management, IT consulting | V3: Myllyoja Janne | W3: janne.myllyoja@knowit.fi | X3: Net 60 days | Y3: X | Z3: X | AA3: Burmeister Jari;Liukkonen Marko;Tapiola Mika | AE3: Pasanen Hannu | AG3: Kuukkanen Markus;INACTIVE Nopanen Atte | AI3: 2025-07-02 TC_SAP_FPER_PORG_OAFP - Valmet Tissue Conv. S.p.A LUCCA (PAP), Indirect procurement iPRO, Office IT proposed by Pollastrini Raffaello | AK3: 646437
B4: twoday oy | C4: twoday oy | D4: HELSINKI | E4: Finland | G4: Active | I4: 42403.682 | K4: 237016 | M4: 392337 | N4: =VLOOKUP(M4,'Spend Export'!$B:$E,4,FALSE) -> #N/A | P4: FI19880693 | Q4: X | R4: Yes | S4: Yes | T4: Indirect procurement iPRO, Office IT, IT consulting;Indirect procurement iPRO, Professional services;Services, R&D engineering;Services, R&D engineering, R&D engineering | U4: Indirect procurement iPRO, Office IT, IT consulting | V4: Dudley Patrick | W4: patrck.dudley@twoday.com | X4: Net 30 days | Z4: X | AA4: Tapiola Mika;Liukkonen Marko | AE4: Pasanen Hannu | AG4: Luhanko Tuomo;Borel Xavier | AI4: 2023-09-12 1001 - Infor LN (AS), Services, R&D engineering, R&D engineering accepted by Kiema Miika | AK4: 322503
B5: Midagon Oy | C5: Midagon Oy | D5: ESPOO | E5: Finland | F5: office@midagon.com | G5: Active | I5: 42361.524 | K5: 236586 | M5: 391845 | N5: =VLOOKUP(M5,'Spend Export'!$B:$E,4,FALSE) -> #N/A | P5: FI20582343 | R5: No | S5: Yes | T5: Indirect procurement iPRO, Office IT, IT consulting;Indirect procurement iPRO, Professional services, Business consulting | U5: Indirect procurement iPRO, Office IT, IT consulting | V5: Viitasalo Jussi | W5: jussi.viitasalo@midagon.com | X5: Net 30 days | Y5: X | AA5: Snedsböl Truls;Liukkonen Marko | AI5: 2025-03-27 Basware - Basware purchasing (Valmet), Indirect procurement iPRO, Professional services, Business consulting accepted by Snedsböl Truls | AK5: 391845
B6: Wipro Limited | C6: Wipro Limited | D6: BANGALORE | E6: India | G6: Active | I6: 42790.42 | K6: 144192 | M6: 404438 | N6: =VLOOKUP(M6,'Spend Export'!$B:$E,4,FALSE) -> #N/A | Q6: X | R6: No | S6: Yes | T6: Indirect procurement iPRO, Office IT, IT consulting | U6: Indirect procurement iPRO, Office IT, IT consulting | V6: Auvray Samuel | W6: samuel.auvray@wipro.com | X6: Net 45 days | Z6: X | AA6: Tapiola Mika;INACTIVE Länsimies Jukka;Liukkonen Marko | AK6: 404438
A7: Deloitte | B7: Deloitte Oy | C7: Deloitte Oy | D7: HELSINKI | E7: Finland | G7: Active | H7: C3 | I7: 38483.505 | K7: 80590 | M7: 210085 | N7: =VLOOKUP(M7,'Spend Export'!$B:$E,4,FALSE) -> 1915873.6 | P7: FI09897715 | R7: Yes | S7: Yes | T7: Indirect procurement iPRO, Professional services, Business consulting | U7: Indirect procurement iPRO, Professional services, Business consulting | V7: Huttu Essi | W7: Essi.Huttu@deloitte.fi | X7: Net 60 days | Z7: X | AG7: INACTIVE Ajo Marja-Liisa | AH7: Snedsböl Truls | AI7: 2025-05-29 1001 - Infor LN (COF) (Valmet), Indirect procurement iPRO, Professional services, Business consulting accepted by Snedsböl Truls | AK7: 210085
B8: Snowflake Computing Netherlands B.V. | C8: Snowflake Computing Netherlands B.V. | D8: AMSTERDAM | E8: Netherlands | G8: Active | I8: 44421.618 | J8: Toropainen Anita | K8: 301945 | M8: 644776 | N8: =VLOOKUP(M8,'Spend Export'!$B:$E,4,FALSE) -> #N/A | P8: NL859338083B01 | R8: Yes | S8: Yes | T8: Indirect procurement iPRO, Office IT, IT consulting | U8: Indirect procurement iPRO, Office IT, IT consulting | V8: Viitala Janne | W8: janne.viitala@snowflake.com | X8: Net 45 days | Z8: X | AI8: 2021-09-08 1001 - Infor LN (PAP), Indirect procurement iPRO, Office IT, IT consulting (Main category) accepted by Tapiola Mika | AK8: 644776
B9: IMD-International Institute for Managem. Develop. | C9: IMD-International Institute for Managem. Develop. | D9: LAUSANNE | E9: Switzerland | G9: Active | I9: 41967.514 | K9: 228311 | M9: 383390 | N9: =VLOOKUP(M9,'Spend Export'!$B:$E,4,FALSE) -> 1524625.8 | P9: CHE-106.448.807 MWST | Q9: X | R9: No | S9: Yes | T9: Indirect procurement iPRO, Personnel, Training & people development | U9: Indirect procurement iPRO, Personnel, Training & people development | X9: Net 60 days | AH9: Korpela Tuija | AK9: 383390
A10: Biisoni | B10: Biisoni Oy | C10: Biisoni Oy | D10: HELSINKI | E10: Finland | F10: info@biisoni.fi | G10: Active | H10: C3 | I10: 40864.475 | K10: 194030 | L10: 539784962 | M10: 344325 | N10: =VLOOKUP(M10,'Spend Export'!$B:$E,4,FALSE) -> 1459890.1 | P10: FI20480777 | Q10: X | R10: No | S10: Yes | T10: Indirect procurement iPRO, Personnel, Leased workforce | U10: Indirect procurement iPRO, Personnel, Leased workforce | V10: Illi Jukka | W10: jukka.illi@biisoni.fi | X10: Net 60 days | Y10: X | Z10: X | AH10: Korpela Tuija | AI10: 2025-02-04 FC - Infor M3 (FC) (FC), Valmet FC Finland Oy 310, Indirect procurement iPRO, Personnel, Leased workforce accepted by Korpela Tuija | AK10: 344325
A11: Dennemeyer | B11: Dennemeyer & Co. Sarl | C11: Dennemeyer & Co. Sarl | D11: HOWALD | E11: Luxembourg | G11: Active | H11: C3 | I11: 37918.593 | K11: 13858 | L11: 400450011 | M11: 606692 | N11: =VLOOKUP(M11,'Spend Export'!$B:$E,4,FALSE) -> 1439973.5 | P11: LU12748436 | R11: No | S11: Yes | T11: Indirect procurement iPRO, Professional services, Patent services | U11: Indirect procurement iPRO, Professional services, Patent services | V11: Fleming Carlene | W11: cfleming@dennemeyer.com | X11: Net 45 days | AK11: 606692
B12: TEec Oy | C12: TEec Oy | D12: JYVÄSKYLÄ | E12: Finland | F12: esa.kivijarvi@teec.fi | G12: Active | I12: 41564.311 | K12: 223187 | M12: 377128 | N12: =VLOOKUP(M12,'Spend Export'!$B:$E,4,FALSE) -> #N/A | P12: FI25773106 | R12: Yes | S12: Yes | T12: Indirect procurement iPRO, Office IT, IT consulting;Services, Mechanical engineering | U12: Indirect procurement iPRO, Office IT, IT consulting | V12: Kivijärvi Esa | W12: esa.kivijarvi@teec.fi | X12: Net 45 days | Z12: X | AA12: Liukkonen Marko;Tapiola Mika | AK12: 377128
B13: Sofigate Oy | C13: Sofigate Oy | D13: ESPOO | E13: Finland | G13: Active | I13: 39399.683 | K13: 116240 | M13: 252501 | N13: =VLOOKUP(M13,'Spend Export'!$B:$E,4,FALSE) -> #N/A | P13: FI19694727 | R13: No | S13: Yes | T13: Indirect procurement iPRO, Office IT, IT consulting | U13: Indirect procurement iPRO, Office IT, IT consulting | V13: Hyppänen Sakari | W13: sakari.hyppanen@sofigate.com | X13: Net 45 days | Y13: X | Z13: X | AA13: Tapiola Mika;Liukkonen Marko;INACTIVE Impersine Christopher | AK13: 252501
B14: Basware Oy | C14: Basware Oy | D14: ESPOO | E14: Finland | G14: Active | I14: 37918.569 | K14: 10822 | L14: 401717137 | M14: 616567 | N14: =VLOOKUP(M14,'Spend Export'!$B:$E,4,FALSE) -> #N/A | P14: FI05925424 | Q14: X | R14: Yes | S14: Yes | T14: Indirect procurement iPRO, Office IT, Application management;Indirect procurement iPRO, Office IT, Application management, IT consulting | U14: Indirect procurement iPRO, Office IT, Application management, IT consulting | V14: Tuomi Jaakko | W14: Jaakko.Tuomi@basware.com | X14: Net 30 days | Z14: X | AA14: Liukkonen Marko;Tapiola Mika | AI14: 2024-12-19 Basware - Basware purchasing (Valmet), Indirect procurement iPRO, Office IT, Application management accepted by Tapiola Mika | AK14: 616567
B15: BearingPoint Finland Oy | C15: BearingPoint Finland Oy | D15: HELSINKI | E15: Finland | G15: Active | I15: 38092.591 | K15: 58113 | M15: 175449 | N15: =VLOOKUP(M15,'Spend Export'!$B:$E,4,FALSE) -> 1359869 | P15: FI17496321 | R15: No | S15: Yes | T15: Indirect procurement iPRO, Professional services, Business consulting | U15: Indirect procurement iPRO, Professional services, Business consulting | V15: Hietanen Tomi | W15: tomi.hietanen@bearingpoint.com | X15: Net 45 days | Y15: X | AA15: INACTIVE Järvinen Janne;INACTIVE Markkanen Jaakko | AK15: 175449
B16: Crayon Oy | C16: Crayon Oy | D16: HELSINKI | E16: Finland | G16: Active | I16: 40304.365 | K16: 152723 | M16: 296632 | N16: =VLOOKUP(M16,'Spend Export'!$B:$E,4,FALSE) -> #N/A | P16: FI20960543 | R16: Yes | S16: Yes | T16: Indirect procurement iPRO, Office IT, Software licenses, IT consulting | U16: Indirect procurement iPRO, Office IT, Software licenses, IT consulting | V16: Johansson Kim | W16: kim.johnsson@crayon.com | X16: Net 30 days | Y16: X | Z16: X | AA16: Vasquez Francisco;Nurmi Riikka;Tapiola Mika;Liukkonen Marko | AI16: 2021-06-01 1001 - Infor LN (COF) (Valmet), Indirect procurement iPRO, Office IT, Software licenses, IT consulting (Main category) accepted by Liukkonen Marko | AK16: 296632
B17: Asianajotoimisto White & Case Oy | C17: Asianajotoimisto White & Case Oy | D17: HELSINKI | E17: Finland | G17: Active | I17: 37928.567 | K17: 37767 | M17: 160710 | N17: =VLOOKUP(M17,'Spend Export'!$B:$E,4,FALSE) -> 1272191.5 | P17: FI09078699 | R17: No | S17: Yes | T17: Indirect procurement iPRO, Professional services, Legal services | U17: Indirect procurement iPRO, Professional services, Legal services | V17: Pesonen Sevi | W17: s.pesonen@whitecase.com | X17: Net 60 days | Z17: X | AH17: INACTIVE Lavonen Antti | AI17: 2021-04-20 1001 - Infor LN (PAP), Indirect procurement iPRO, Professional services, Legal services (Main category) accepted by Mäkelä Henri | AK17: 160710
A18: Adecco Group AG | B18: Adecco Finland Oy | C18: Adecco Finland Oy | D18: VANTAA | E18: Finland | F18: adecco@adecco.fi | G18: Active | H18: C3 | I18: 39948.548 | K18: 137126 | L18: 651501934 | M18: 278118 | N18: =VLOOKUP(M18,'Spend Export'!$B:$E,4,FALSE) -> 1271566.2 | P18: FI10424640 | Q18: X | R18: Yes | S18: Yes | T18: Indirect procurement iPRO, Personnel, Leased workforce | U18: Indirect procurement iPRO, Personnel, Leased workforce | V18: Hänninen Henri | W18: henri.hanninen@adecco.fi | X18: Net 60 days | Y18: X | Z18: X | AE18: Tamminen Jari | AH18: Korpela Tuija | AI18: 2024-12-19 Workday - Workday Leased workforce (Valmet), Indirect procurement iPRO, Personnel, Leased workforce accepted by Korpela Tuija | AK18: 278118
B19: ServiceMax Inc. | C19: ServiceMax Inc. | D19: PLEASANTON | E19: United States | G19: Active | I19: 43703.581 | J19: INACTIVE Uusitalo Jukka | K19: 291503 | M19: 631492 | N19: =VLOOKUP(M19,'Spend Export'!$B:$E,4,FALSE) -> #N/A | Q19: X | R19: No | S19: Yes | T19: Indirect procurement iPRO, Office IT, Software licenses, Application management, IT consulting | U19: Indirect procurement iPRO, Office IT, Software licenses, Application management, IT consulting | V19: Rogers Glyn | W19: glyn.rogers@servicemax.com | X19: Net 45 days | Z19: X | AA19: Tapiola Mika;Liukkonen Marko | AI19: 2019-08-28 1001 - Infor LN (COF) (Valmet), Indirect procurement iPRO, Office IT, Software licenses, Application management, IT consulting (Main category) accepted by Tapiola Mika | AK19: 631492
B20: Danske Bank A/S, Suomen sivuliike | C20: Danske Bank A/S, Suomen sivuliike | D20: HELSINKI | E20: Finland | G20: Active | I20: 41787.614 | K20: 221482 | M20: 381110 | N20: =VLOOKUP(M20,'Spend Export'!$B:$E,4,FALSE) -> 1139926.1 | P20: FI10786932 | R20: No | S20: Yes | T20: Indirect procurement iPRO, Professional services, Business consulting;Indirect procurement iPRO, Taxes and charges, Other regulatory charges | U20: Indirect procurement iPRO, Professional services, Business consulting | V20: Kivimäki Tuomas | W20: tuomas.kivimaki@danskebank.com | X20: Net 14 days | AG20: Aalto Janne;Savolainen Olli | AI20: 2024-05-30 FC - Infor M3 (FC) (FC), Valmet FC Finland Oy 310, Indirect procurement iPRO, Taxes and charges, Other regulatory charges accepted by Mäkelä Henri | AK20: 381110
A21: PriceWaterhouseCoopers LLP | B21: PricewaterhouseCoopers Oy | C21: PricewaterhouseCoopers Oy | D21: HELSINKI | E21: Finland | F21: laskutus.kyselyt@fi.pwc.com | G21: Active | H21: C3 | I21: 37928.615 | K21: 28516 | L21: 368999884 | M21: 162976 | N21: =VLOOKUP(M21,'Spend Export'!$B:$E,4,FALSE) -> 1114989.2 | P21: FI04864068 | R21: No | S21: Yes | T21: Indirect procurement iPRO, Professional services, Business consulting | U21: Indirect procurement iPRO, Professional services, Business consulting | V21: Puukkoniemi Tiina | W21: Tiina.Puukkoniemi@pwc.com | X21: Net 7 days | Z21: X | AA21: Snedsböl Truls | AK21: 162976
B22: Finitec Oy | C22: Finitec Oy | D22: HELSINKI | E22: Finland | F22: reskontra@finitec.fi | G22: Active | I22: 42135.425 | K22: 230688 | M22: 631160 | N22: =VLOOKUP(M22,'Spend Export'!$B:$E,4,FALSE) -> 984321 | P22: FI24547254 | R22: No | S22: Yes | T22: Indirect procurement iPRO, Professional services, Business consulting;Indirect procurement iPRO, Professional services, R&D services & materials;Services, Automation engineering, Automation engineering | U22: Indirect procurement iPRO, Professional services, Business consulting | V22: Martinsuo Teppo | W22: teppo.martinsuo@finitec.fi | X22: Net 45 days | Z22: X | AE22: Pasanen Hannu | AI22: 2023-02-28 FC - Infor M3 (FC) (FC), Indirect procurement iPRO, Professional services, R&D services & materials accepted by Kiema Miika | AK22: 295650
A23: Biisoni | B23: Biisoni Tampere Oy | C23: Biisoni Tampere Oy | D23: HELSINKI | E23: Finland | G23: Active | H23: C3 | I23: 43178.445 | J23: INACTIVE Vakkuri Jarmo | K23: 285890 | M23: 623840 | N23: =VLOOKUP(M23,'Spend Export'!$B:$E,4,FALSE) -> 949359.13 | P23: FI23981569 | Q23: X | R23: Yes | S23: Yes | T23: Indirect procurement iPRO, Personnel, Leased workforce;Services, Subcontracted production capacity, Workforce of subassemblies or assemblies | U23: Indirect procurement iPRO, Personnel, Leased workforce | V23: Illi Jukka | W23: jukka.illi@biisoni.fi | X23: Net 60 days | Y23: X | Z23: X | AA23: Korpela Tuija | AI23: 2025-01-08 Basware - Basware purchasing (Valmet), Indirect procurement iPRO, Personnel, Leased workforce accepted by Korpela Tuija | AK23: 623840
B24: GoMetan III Oy | C24: GoMetan III Oy | D24: JYVÄSKYLÄ | E24: Finland | F24: jyvaskyla@go-on.fi | G24: Active | I24: 43780.543 | J24: Hämäläinen Seppo J | K24: 292621 | L24: 368667988 | M24: 632993 | N24: =VLOOKUP(M24,'Spend Export'!$B:$E,4,FALSE) -> 786589.18 | P24: FI29893586 | R24: No | S24: Yes | T24: Indirect procurement iPRO, Personnel, Leased workforce | U24: Indirect procurement iPRO, Personnel, Leased workforce | V24: Salminen Kimmo | W24: kimmo.salminen@go-on.fi | X24: Net 60 days | Z24: X | AH24: Korpela Tuija | AI24: 2025-01-08 Basware - Basware purchasing (Valmet), Indirect procurement iPRO, Personnel, Leased workforce accepted by Korpela Tuija | AK24: 632993
B25: Nigel Frank International | C25: Nigel Frank International | D25: NEWCASTLE UPON TYNE | E25: United Kingdom | G25: Active | I25: 44589.568 | J25: Latini Luca | K25: 303792 | M25: 647811 | N25: =VLOOKUP(M25,'Spend Export'!$B:$E,4,FALSE) -> #N/A | P25: GB164369978 | R25: No | S25: Yes | T25: Indirect procurement iPRO, Office IT, IT consulting;Indirect procurement iPRO, Professional services, Business consulting | U25: Indirect procurement iPRO, Office IT, IT consulting | V25: Nevin Matthew | W25: m.nevin@nigelfrank.com | X25: Net 30 days | AI25: 2022-02-03 1001 - Infor LN (COF) (Valmet), Indirect procurement iPRO, Professional services, Business consulting accepted by Mäkelä Henri | AK25: 647811
B26: Berggren Oy | C26: Berggren Oy | D26: HELSINKI | E26: Finland | G26: Active | I26: 42033.593 | K26: 229099 | M26: 384283 | N26: =VLOOKUP(M26,'Spend Export'!$B:$E,4,FALSE) -> 745709.07 | P26: FI26358991 | R26: No | S26: Yes | T26: Indirect procurement iPRO, Professional services, Patent services | U26: Indirect procurement iPRO, Professional services, Patent services | V26: Kantanen Jukka | W26: jukka.kantanen@berggren.fi | X26: Net 60 days | AI26: 2024-08-12 FC - Infor M3 (FC) (FC), Valmet FC Finland Oy 310, Indirect procurement iPRO, Professional services, Patent services accepted by Snedsböl Truls | AK26: 384283
B27: ManpowerGroup Oy | C27: ManpowerGroup Oy | D27: HELSINKI | E27: Finland | G27: Active | I27: 37918.711 | K27: 24042 | L27: 651884397 | M27: 607060 | N27: =VLOOKUP(M27,'Spend Export'!$B:$E,4,FALSE) -> 738534.05 | P27: FI10910323 | Q27: X | R27: Yes | S27: Yes | T27: Indirect procurement iPRO, Personnel, Leased workforce | U27: Indirect procurement iPRO, Personnel, Leased workforce | V27: Karlsson Piia | W27: piia.karlsson@manpowergroup.fi | X27: Net 60 days | Z27: X | AA27: Korpela Tuija | AI27: 2025-01-08 Basware - Basware purchasing (Valmet), Indirect procurement iPRO, Personnel, Leased workforce accepted by Korpela Tuija | AK27: 607060
A28: KPMG International | B28: KPMG Oy Ab | C28: KPMG Oy Ab | D28: HELSINKI | E28: Finland | F28: contact@kpmg.fi | G28: Active | H28: C3 | I28: 37918.683 | K28: 21976 | M28: 600689 | N28: =VLOOKUP(M28,'Spend Export'!$B:$E,4,FALSE) -> 711573.76 | P28: FI18054859 | R28: Yes | S28: Yes | T28: Indirect procurement iPRO, Professional services, Business consulting;Indirect procurement iPRO, Professional services, Certification, standardization & audits;Indirect procurement iPRO, Taxes and charges;Indirect procurement iPRO, Taxes and charges, Taxes;Services, Site management and services, Other expert services at site | U28: Indirect procurement iPRO, Professional services, Business consulting | V28: Tiitta Erkki | W28: erkki.tiitta@kpmg.fi | X28: Net 30 days | Z28: X | AA28: Ruusuvaara Petri | AG28: INACTIVE Mariana Erna | AH28: Burmeister Jari;Snedsböl Truls | AI28: 2020-09-15 368 - Valmet (China) Co., Ltd. (SHA) (PAP), Indirect procurement iPRO, Professional services, Certification, standardization & audits accepted by INACTIVE Su Yanjing | AK28: 600689
B29: Fluentscale Oy | C29: Fluentscale Oy | D29: VANTAA | E29: Finland | G29: Active | I29: 42893.593 | K29: 249278 | M29: 406410 | N29: =VLOOKUP(M29,'Spend Export'!$B:$E,4,FALSE) -> #N/A | P29: FI26042663 | R29: No | S29: Yes | T29: Indirect procurement iPRO, Office IT, IT consulting | U29: Indirect procurement iPRO, Office IT, IT consulting | V29: Seppänen Sami | W29: sami.seppanen@fluentscale.fi | X29: Net 45 days | Z29: X | AG29: Rautiainen Mikko | AK29: 406410
B30: Edward Lynx AB | C30: Edward Lynx AB | D30: STOCKHOLM | E30: Sweden | F30: info@edwardlynx.com | G30: Active | I30: 42795.415 | K30: 247559 | M30: 404521 | N30: =VLOOKUP(M30,'Spend Export'!$B:$E,4,FALSE) -> 692085 | P30: SE556546088701 | Q30: X | R30: No | S30: Yes | T30: Indirect procurement iPRO, Personnel, Training & people development;Indirect procurement iPRO, Professional services, Other business services | U30: Indirect procurement iPRO, Personnel, Training & people development | V30: Wretling Ola | W30: ola.wretling@edwardlynx.com | X30: Net 60 days | Y30: X | Z30: X | AH30: Korpela Tuija | AI30: 2023-08-14 FC - Infor M3 (FC) (FC), Indirect procurement iPRO, Personnel, Training & people development accepted by Mäkelä Henri | AK30: 404521
B31: Saltire Projects Limited | C31: Saltire Projects Limited | D31: ABERDEEN | E31: United Kingdom | F31: enquiries@saltireprojects.co.uk | G31: Active | I31: 40218.454 | K31: 148491 | M31: 291824 | N31: =VLOOKUP(M31,'Spend Export'!$B:$E,4,FALSE) -> 605687.1 | P31: GB239300719 | R31: Yes | S31: Yes | T31: Indirect procurement iPRO, Professional services, Business consulting;Indirect procurement iPRO, Professional services, Legal services | U31: Indirect procurement iPRO, Professional services, Business consulting | V31: Adams Keith | W31: keithadams@saltireprojects.co.uk | X31: Net 30 days | Z31: X | AG31: Takala Arto | AI31: 2021-04-16 634 - Valmet Technologies, Inc FIB Pori (MP) (P&E), Indirect procurement iPRO, Professional services, Legal services accepted by Mäkelä Henri | AK31: 291824
B32: Nixu Oy | C32: Nixu Oy | D32: ESPOO | E32: Finland | G32: Active | I32: 40490.605 | K32: 163890 | M32: 309965 | N32: =VLOOKUP(M32,'Spend Export'!$B:$E,4,FALSE) -> #N/A | P32: FI07218117 | Q32: X | R32: No | S32: Yes | T32: Indirect procurement iPRO, Office IT, Software licenses, IT consulting | U32: Indirect procurement iPRO, Office IT, Software licenses, IT consulting | V32: Relander Veera | W32: veera.relander@dnv.com | X32: Net 45 days | Y32: X | Z32: X | AA32: Majaharju Matias;Tapiola Mika;Liukkonen Marko | AK32: 309965
B33: Zure Oy | C33: Zure Oy | D33: HELSINKI | E33: Finland | G33: Active | I33: 43752.511 | J33: INACTIVE Rantalainen Lasse | K33: 292910 | L33: 539828695 | M33: 632449 | N33: =VLOOKUP(M33,'Spend Export'!$B:$E,4,FALSE) -> #N/A | P33: FI24161239 | R33: Yes | S33: Yes | T33: Indirect procurement iPRO, Office IT, IT consulting | U33: Indirect procurement iPRO, Office IT, IT consulting | V33: Nahi Sakari | W33: sakari.nahi@zure.com | X33: Net 45 days | Z33: X | AA33: Tapiola Mika;Liukkonen Marko | AE33: Pasanen Hannu | AI33: 2024-11-28 Basware - Basware purchasing (Valmet), Indirect procurement iPRO, Office IT, IT consulting accepted by Tapiola Mika | AK33: 632449
B34: itdesign GmbH | C34: itdesign GmbH | D34: TUEBINGEN | E34: Germany | G34: Active | I34: 44232.379 | J34: Toropainen Anita | K34: 298858 | M34: 640953 | N34: =VLOOKUP(M34,'Spend Export'!$B:$E,4,FALSE) -> #N/A | P34: DE203913579 | R34: Yes | S34: Yes | T34: Indirect procurement iPRO, Office IT, IT consulting | U34: Indirect procurement iPRO, Office IT, IT consulting | V34: Hartwich Bianca | W34: bianca.hartwich@itdesign.de | X34: Net 45 days | Y34: X | Z34: X | AA34: Liukkonen Marko | AI34: 2021-02-15 1001 - Infor LN (PAP), Indirect procurement iPRO, Office IT, IT consulting (Main category) accepted by Tapiola Mika | AK34: 640953
B35: ManTec AB | C35: ManTec AB | D35: GOTHENBURG | E35: Sweden | F35: mantec@mantec.eu | G35: Active | I35: 45055.706 | J35: Olsson Åke | K35: 316166 | M35: 663937 | N35: =VLOOKUP(M35,'Spend Export'!$B:$E,4,FALSE) -> 522745 | P35: SE556717793501 | R35: No | S35: Yes | T35: Indirect procurement iPRO, Professional services, Business consulting | U35: Indirect procurement iPRO, Professional services, Business consulting | V35: Johannission Håkan | W35: hakan.johannisson@mantec.eu | X35: Net 60 days | AI35: 2023-07-07 642 - SER (SWE) (SER), Indirect procurement iPRO, Professional services, Business consulting (Main category) accepted by Snedsböl Truls | AK35: 663937
A36: Digia | B36: Digia Finland Oy | C36: Digia Finland Oy | D36: HELSINKI | E36: Finland | F36: digia.finland@bscs.basware.com | G36: Active | H36: C3 | I36: 38569.687 | K36: 87697 | M36: 218764 | N36: =VLOOKUP(M36,'Spend Export'!$B:$E,4,FALSE) -> #N/A | P36: FI10912484 | R36: No | S36: Yes | T36: Indirect procurement iPRO, Office IT, Application management;Indirect procurement iPRO, Office IT, IT consulting | U36: Indirect procurement iPRO, Office IT, IT consulting | V36: Tumanoff Tommi | W36: tommi.tumanoff@digia.com | X36: Net 30 days | Z36: X | AA36: Tapiola Mika;Liukkonen Marko | AK36: 218764
B37: Sweden Modular Management AB | C37: Sweden Modular Management AB | D37: STOCKHOLM | E37: Sweden | F37: info@modularmanagement.com | G37: Active | I37: 41954.494 | K37: 228153 | M37: 383188 | N37: =VLOOKUP(M37,'Spend Export'!$B:$E,4,FALSE) -> 478302.71 | P37: SE556982984801 | R37: Yes | S37: Yes | T37: Indirect procurement iPRO, Professional services, R&D services & materials | U37: Indirect procurement iPRO, Professional services, R&D services & materials | V37: Berggren Peter | W37: peter.berggren@modularmanagement.com | X37: Net 45 days | Z37: X | AH37: Snedsböl Truls | AK37: 383188
B38: Rekrytointipalvelu Sihti Oy | C38: Rekrytointipalvelu Sihti Oy | D38: TAMPERE | E38: Finland | F38: laskutus@sihti.fi | G38: Active | I38: 42199.436 | K38: 231530 | L38: 651294964 | M38: 386990 | N38: =VLOOKUP(M38,'Spend Export'!$B:$E,4,FALSE) -> 453472.05 | P38: FI22425579 | R38: No | S38: Yes | T38: Indirect procurement iPRO, Personnel, Leased workforce | U38: Indirect procurement iPRO, Personnel, Leased workforce | V38: Lindgren Joni | W38: joni.lindgren@sihti.fi | X38: Net 60 days | Y38: X | AG38: Kuru Antti | AI38: 2024-11-05 Basware - Basware purchasing (Valmet), Indirect procurement iPRO, Personnel, Leased workforce accepted by Korpela Tuija | AK38: 386990
B39: Taitopilvi Oy | C39: Taitopilvi Oy | D39: JYVÄSKYLÄ | E39: Finland | G39: Active | I39: 43005.65 | J39: Majaharju Matias | K39: 284255 | M39: 621542 | N39: =VLOOKUP(M39,'Spend Export'!$B:$E,4,FALSE) -> #N/A | P39: FI27861337 | R39: No | S39: Yes | T39: Indirect procurement iPRO, Office IT, Application management, IT consulting;Indirect procurement iPRO, Professional services, Other business services | U39: Indirect procurement iPRO, Office IT, Application management, IT consulting | V39: Heinola Matti | W39: matti.heinola@taitopilvi.fi | X39: Net 30 days | Z39: X | AA39: Tapiola Mika;Liukkonen Marko;Majaharju Matias | AI39: 2017-11-01 639 - Valmet Technologies, Inc PPP HO (MP) (Valmet), Indirect procurement iPRO, Professional services, Other business services accepted by Mäkelä Henri | AK39: 621542
B40: Melkki Partners Oy | C40: Melkki Partners Oy | D40: HELSINKI | E40: Finland | G40: Active | I40: 44749.439 | J40: Liukkonen Marko | K40: 306128 | M40: 650578 | N40: =VLOOKUP(M40,'Spend Export'!$B:$E,4,FALSE) -> #N/A | P40: FI32049917 | R40: No | S40: Yes | T40: Indirect procurement iPRO, Office IT, IT consulting | U40: Indirect procurement iPRO, Office IT, IT consulting | V40: Felixson Patrik | W40: patrik.felixson@melkki.fi | X40: Net 45 days | Z40: X | AA40: Liukkonen Marko;Tapiola Mika | AI40: 2022-08-15 1001 - Infor LN (COF) (Valmet), Indirect procurement iPRO, Office IT, IT consulting (Main category) accepted by Tapiola Mika | AK40: 650578
B41: Gartner Finland Oy | C41: Gartner Finland Oy | D41: ESPOO | E41: Finland | G41: Active | I41: 37918.713 | K41: 24134 | M41: 602494 | N41: =VLOOKUP(M41,'Spend Export'!$B:$E,4,FALSE) -> #N/A | P41: FI06128021 | R41: No | S41: Yes | T41: Indirect procurement iPRO, Office IT, IT consulting | U41: Indirect procurement iPRO, Office IT, IT consulting | V41: Tiainen Ville | W41: ville.tiainen@gartner.com | X41: Net 45 days | AG41: INACTIVE Felin Anu | AK41: 602494
A42: Kiwa | B42: Kiwa Impact Oy | C42: Imatra | D42: IMATRA | E42: Finland | F42: info@lis.fi | G42: Active | H42: C3 | I42: 40086.435 | K42: 294828 | M42: 284620 | N42: =VLOOKUP(M42,'Spend Export'!$B:$E,4,FALSE) -> 345458.51 | P42: FI20879323 | R42: Yes | S42: Yes | T42: Indirect procurement iPRO, Personnel, Training & people development;Indirect procurement iPRO, Professional services, Testing, measurement & inspection | U42: Indirect procurement iPRO, Professional services, Testing, measurement & inspection | V42: Svartsjö-Villacorta Taija | W42: toimisto@lis.fi | X42: Net 60 days | Y42: X | Z42: X | AH42: Snedsböl Truls | AI42: 2020-10-02 631 - Valmet Technologies, Inc PM (MP) (PAP), Indirect procurement iPRO, Personnel, Training & people development accepted by Mäkelä Henri | AK42: 284620
A43: TietoEVRY Oyj | B43: Tietoevry Finland Oy | C43: Tietoevry Finland Oy | D43: ESPOO | E43: Finland | G43: Active | H43: C3 | I43: 39854.599 | K43: 131904 | L43: 459905498 | M43: 272674 | N43: =VLOOKUP(M43,'Spend Export'!$B:$E,4,FALSE) -> #N/A | P43: FI19623611 | R43: Yes | S43: Yes | T43: Indirect procurement iPRO, Office IT, IT consulting | U43: Indirect procurement iPRO, Office IT, IT consulting | V43: Rintanen Lassi | W43: lassi.rintanen@tietoevry.com | X43: Net 30 days | Y43: X | AG43: INACTIVE Ajo Marja-Liisa | AK43: 272674
B44: Nagarro Oy | C44: Nagarro Oy | D44: ESPOO | E44: Finland | G44: Active | I44: 44640.658 | J44: Virnes Markku | K44: 304426 | M44: 648708 | N44: =VLOOKUP(M44,'Spend Export'!$B:$E,4,FALSE) -> #N/A | P44: FI28101241 | R44: No | S44: Yes | T44: Indirect procurement iPRO, Office IT, IT consulting | U44: Indirect procurement iPRO, Office IT, IT consulting | V44: Upmanyu Dhananjay | W44: dhananjay.upmanyu@nagarro.com | X44: Net 30 days | Z44: X | AA44: Tapiola Mika | AG44: Salo Sami;Frisk Sami | AI44: 2022-03-20 Indirect procurement iPRO, Office IT, IT consulting (Main category) accepted by | AK44: 648708
B45: Washington Frank | C45: Washington Frank | D45: LONDON | E45: United Kingdom | G45: Active | I45: 43627.524 | J45: INACTIVE Nevalainen Merja H | K45: 290715 | M45: 630464 | N45: =VLOOKUP(M45,'Spend Export'!$B:$E,4,FALSE) -> #N/A | R45: No | S45: Yes | T45: Indirect procurement iPRO, Office IT, IT consulting | U45: Indirect procurement iPRO, Office IT, IT consulting | V45: Nevin Matthew | W45: m.nevin@washingtonfrank.com | X45: Net 30 days | Z45: X | AG45: INACTIVE Nevalainen Merja H | AI45: 2019-06-11 1001 - Infor LN (SER), Indirect procurement iPRO, Office IT, IT consulting (Main category) accepted by Tapiola Mika | AK45: 630464
B46: Kenttäviiva Oy Automaatio | C46: Kenttäviiva Oy Automaatio | D46: TURKU | E46: Finland | F46: kenttaviiva@kenttaviiva.fi | G46: Active | I46: 38839.592 | K46: 96396 | M46: 228861 | N46: =VLOOKUP(M46,'Spend Export'!$B:$E,4,FALSE) -> 323750.97 | P46: FI20181320 | R46: Yes | S46: Yes | T46: Indirect procurement iPRO, Professional services, R&D services & materials | U46: Indirect procurement iPRO, Professional services, R&D services & materials | V46: Kontto Antti | W46: antti.kontto@kenttaviiva.fi | X46: Net 45 days | Y46: X | Z46: X | AG46: Kettunen Heikki | AK46: 228861
B47: Teknologian tutkimuskeskus VTT Oy | C47: Vuorimiehentie | D47: ESPOO | E47: Finland | F47: name.surname@vtt.fi | G47: Active | I47: 38777.586 | K47: 37156 | L47: 368919580 | M47: 226170 | N47: =VLOOKUP(M47,'Spend Export'!$B:$E,4,FALSE) -> 322874.51 | P47: FI26473754 | R47: Yes | S47: Yes | T47: Indirect procurement iPRO, Professional services, R&D services & materials | U47: Indirect procurement iPRO, Professional services, R&D services & materials | V47: Kuusisaari Jaakko | W47: jaakko.kuusisaari@vtt.fi | X47: Net 45 days | Z47: X | AG47: INACTIVE Ajo Marja-Liisa | AH47: Snedsböl Truls | AK47: 226170
B48: Cescon, Barrieu, Flesch, Barreto e Teixeira | C48: Cescon, Barrieu, Flesch, Barreto e Teixeira | D48: RIO DE JANEIRO | E48: Brazil | G48: Active | I48: 44896.659 | J48: INACTIVE Batalha-Keskinen Anna | K48: 310872 | M48: 656950 | N48: =VLOOKUP(M48,'Spend Export'!$B:$E,4,FALSE) -> 290940.8 | R48: No | S48: Yes | T48: Indirect procurement iPRO, Professional services, Legal services | U48: Indirect procurement iPRO, Professional services, Legal services | V48: Billing Department | W48: faturamento@cesconbarrieu.com.br | X48: Net 60 days | AI48: 2022-12-01 1001 - Infor LN (COF) (Valmet), Indirect procurement iPRO, Professional services, Legal services (Main category) accepted by Snedsböl Truls | AK48: 656950
B49: Neuvolab Oy | C49: Neuvolab Oy | D49: TAMPERE | E49: Finland | G49: Active | I49: 44124.422 | J49: Toropainen Anita | K49: 297908 | M49: 639365 | N49: =VLOOKUP(M49,'Spend Export'!$B:$E,4,FALSE) -> #N/A | P49: FI31628474 | R49: No | S49: Yes | T49: Indirect procurement iPRO, Office IT, IT consulting | U49: Indirect procurement iPRO, Office IT, IT consulting | V49: Onnela Nona | W49: nona.onnela@neuvolab.fi | X49: Net 60 days | Y49: X | Z49: X | AA49: INACTIVE Pouhula Sami;Tapiola Mika;Liukkonen Marko | AI49: 2020-11-12 1001 - Infor LN (PAP), Indirect procurement iPRO, Office IT, IT consulting (Main category) accepted by Tapiola Mika | AK49: 639365
B50: Neomore Consulting Oy | C50: Neomore Consulting Oy | D50: ESPOO | E50: Finland | F50: sales@neomore.fi | G50: Active | I50: 40829.639 | K50: 191054 | M50: 340888 | N50: =VLOOKUP(M50,'Spend Export'!$B:$E,4,FALSE) -> #N/A | P50: FI10569815 | R50: No | S50: Yes | T50: Indirect procurement iPRO, Office IT, IT consulting | U50: Indirect procurement iPRO, Office IT, IT consulting | V50: Björkqvist Peter | W50: peter.bjorkqvist@neomore.fi | X50: Net 30 days | Z50: X | AA50: Nieminen Eija | AK50: 340888
B51: Nomentia Oy | C51: Nomentia Oy | D51: ESPOO | E51: Finland | G51: Active | I51: 38043.72 | K51: 46022 | M51: 635744 | N51: =VLOOKUP(M51,'Spend Export'!$B:$E,4,FALSE) -> #N/A | P51: FI28555577 | R51: No | S51: Yes | T51: Indirect procurement iPRO, Office IT, Application management, IT consulting;Indirect procurement iPRO, Office IT, Servers & other hardware | U51: Indirect procurement iPRO, Office IT, Servers & other hardware | V51: Haimila Matti | W51: matti.haimila@opuscapita.com | X51: Net 45 days | Z51: X | AA51: Laitinen Saija | AI51: 2020-08-06 1001 - Infor LN (COF) (Valmet), Indirect procurement iPRO, Office IT, Application management, IT consulting (Main category) accepted by Tapiola Mika | AK51: 168349
B52: Energy Opticon AB | C52: Energy Opticon AB | D52: LUND | E52: Sweden | F52: info@opticon.se | G52: Active | I52: 40687.546 | K52: 184255 | M52: 333232 | N52: =VLOOKUP(M52,'Spend Export'!$B:$E,4,FALSE) -> 256267.29 | P52: SE556390947101 | Q52: X | R52: Yes | S52: Yes | T52: Indirect procurement iPRO, Professional services, R&D services & materials | U52: Indirect procurement iPRO, Professional services, R&D services & materials | V52: Malmström Björn | W52: bjorn.malmstrom@opticon.se | X52: Net 45 days | Y52: X | Z52: X | AE52: Pasanen Hannu | AK52: 333232
A53: Alfa Quality | B53: Alfa Mobility Finland Oy | C53: Alfa Mobility Finland Oy | D53: HELSINKI | E53: Finland | F53: info@alfamoving.fi | G53: Active | H53: C3 | I53: 39072.65 | K53: 106510 | M53: 241134 | N53: =VLOOKUP(M53,'Spend Export'!$B:$E,4,FALSE) -> 255766.35 | P53: FI20495362 | Q53: X | R53: Yes | S53: Yes | T53: Indirect procurement iPRO, Professional services, Business consulting | U53: Indirect procurement iPRO, Professional services, Business consulting | V53: Westerholm Dennis | W53: dennis.westerholm@alfamoving.com | X53: Net 60 days | Z53: X | AH53: Snedsböl Truls | AK53: 241134
A54: Tata Group | B54: Tata Consultancy Services Limited | C54: Mumbai (Nirmal) Registered Office | D54: MUMBAI | E54: India | G54: Active | H54: C3 | I54: 44640.658 | J54: Virnes Markku | K54: 196830 | M54: 648706 | N54: =VLOOKUP(M54,'Spend Export'!$B:$E,4,FALSE) -> #N/A | R54: No | S54: Yes | T54: Indirect procurement iPRO, Office IT, IT consulting | U54: Indirect procurement iPRO, Office IT, IT consulting | V54: Samantray Subhadipta | W54: s.samantray@tcs.com | X54: Net 45 days | AA54: Tapiola Mika | AI54: 2022-03-20 Indirect procurement iPRO, Office IT, IT consulting (Main category) accepted by | AK54: 648706
A55: AFRY | B55: AFRY Management Consulting Oy | C55: AFRY Management Consulting Oy | D55: VANTAA | E55: Finland | G55: Active | H55: C3 | I55: 40204.558 | K55: 147791 | M55: 290981 | N55: =VLOOKUP(M55,'Spend Export'!$B:$E,4,FALSE) -> #N/A | P55: FI23022763 | R55: Yes | S55: Yes | T55: Indirect procurement iPRO, Office IT, IT consulting;Indirect procurement iPRO, Professional services, Business consulting | U55: Indirect procurement iPRO, Office IT, IT consulting | V55: Turkkila Kalle | W55: kalle.turkkila@afry.com | X55: Net 45 days | AA55: Kiema Miika | AI55: 2021-10-12 304 - LAE Production T3.4 (LAE) (SER), Indirect procurement iPRO, Professional services, Business consulting accepted by Monprasit Kobporn | AK55: 290981
B56: Kolster Oy Ab | C56: Kolster Oy Ab | D56: HELSINKI | E56: Finland | F56: kolster@kolster.fi | G56: Active | I56: 37928.592 | K56: 38865 | M56: 161884 | N56: =VLOOKUP(M56,'Spend Export'!$B:$E,4,FALSE) -> 241010.86 | P56: FI01101292 | R56: No | S56: Yes | T56: Indirect procurement iPRO, Professional services, Patent services | U56: Indirect procurement iPRO, Professional services, Patent services | V56: Kolster General | W56: kolster@kolster.com | X56: Net 45 days | AK56: 161884
B57: Sulava Oy | C57: Sulava Oy | D57: HELSINKI | E57: Finland | F57: info@sulava.com | G57: Active | I57: 43620.326 | J57: INACTIVE Mantere Mika | K57: 290761 | M57: 630353 | N57: =VLOOKUP(M57,'Spend Export'!$B:$E,4,FALSE) -> #N/A | P57: FI23710689 | R57: No | S57: Yes | T57: Indirect procurement iPRO, Office IT, IT consulting;Indirect procurement iPRO, Personnel, Training & people development | U57: Indirect procurement iPRO, Office IT, IT consulting | V57: Antman Aki | W57: aki.antman@sulava.com | X57: Net 60 days | Z57: X | AH57: Kiema Miika | AI57: 2019-06-11 FI310A - Valmet Automation Finland (AS), Indirect procurement iPRO, Personnel, Training & people development accepted by Mäkelä Henri | AK57: 630353
B58: Forward Forever | C58: Forward Forever | D58: HELSINKI | E58: Finland | G58: Active | I58: 44334.581 | J58: INACTIVE Da Conceicao Sari | K58: 300579 | M58: 643120 | N58: =VLOOKUP(M58,'Spend Export'!$B:$E,4,FALSE) -> #N/A | P58: FI31126132 | R58: No | S58: Yes | T58: Indirect procurement iPRO, Office IT, IT consulting | U58: Indirect procurement iPRO, Office IT, IT consulting | V58: Nyholm Jouko | W58: jouko.nyholm@forwardforever.com | X58: Net 60 days | Z58: X | AA58: INACTIVE Da Conceicao Sari;Liukkonen Marko | AI58: 2025-06-18 Basware - Basware purchasing (Valmet), Indirect procurement iPRO, Office IT, IT consulting accepted by Mäkelä Henri | AK58: 643120
B59: Islet Intelligence Oy | C59: Islet Intelligence Oy | D59: ESPOO | E59: Finland | G59: Active | I59: 44573.607 | J59: Toropainen Anita | K59: 304014 | M59: 647396 | N59: =VLOOKUP(M59,'Spend Export'!$B:$E,4,FALSE) -> #N/A | P59: FI32074768 | R59: No | S59: Yes | T59: Indirect procurement iPRO, Office IT, IT consulting | U59: Indirect procurement iPRO, Office IT, IT consulting | V59: Luoto Janina | W59: janina.luoto@isletgroup.fi | X59: Net 45 days | Z59: X | AA59: Liukkonen Marko;Soikkanen Sirpa | AI59: 2022-02-10 1001 - Infor LN (PAP), Indirect procurement iPRO, Office IT, IT consulting (Main category) accepted by Tapiola Mika | AK59: 647396
B60: Lecklé Alvia Oy | C60: Lecklé Alvia Oy | D60: TAMPERE | E60: Finland | F60: hanna.huhtala@leckle.fi | G60: Active | I60: 44412.543 | J60: Mähönen-Mendoza Emma | K60: 301513 | M60: 656509 | N60: =VLOOKUP(M60,'Spend Export'!$B:$E,4,FALSE) -> 227200 | P60: FI33122573 | R60: No | S60: Yes | T60: Indirect procurement iPRO, Professional services, Business consulting | U60: Indirect procurement iPRO, Professional services, Business consulting | V60: Huhtala Hanna | W60: hanna.huhtala@leckle.fi | X60: Net 60 days | Y60: X | AG60: Ndiritu Grace | AI60: 2021-08-06 1001 - Infor LN (COF) (Valmet), Indirect procurement iPRO, Professional services, Business consulting (Main category) accepted by Mäkelä Henri | AK60: 644626
B61: Krios Business Consulting Oy | C61: Krios Business Consulting Oy | D61: ESPOO | E61: Finland | G61: Active | I61: 43505.528 | J61: Toropainen Anita | K61: 289809 | M61: 628626 | N61: =VLOOKUP(M61,'Spend Export'!$B:$E,4,FALSE) -> #N/A | P61: FI27798753 | R61: No | S61: Yes | T61: Indirect procurement iPRO, Office IT, IT consulting | U61: Indirect procurement iPRO, Office IT, IT consulting | V61: Sääksvuori Antti | W61: antti.saaksvuori@krios.fi | X61: Net 60 days | Z61: X | AA61: Korhonen Pauli | AI61: 2019-03-15 1001 - Infor LN (SER), Indirect procurement iPRO, Office IT, IT consulting accepted by INACTIVE Vaiste Ismo | AK61: 628626
B62: Roschier Brands Asianajotoimisto Oy | C62: Roschier Brands Asianajotoimisto Oy | D62: HELSINKI | E62: Finland | G62: Active | I62: 37918.571 | K62: 11039 | M62: 506965 | N62: =VLOOKUP(M62,'Spend Export'!$B:$E,4,FALSE) -> 222334.08 | P62: FI10243620 | R62: No | S62: Yes | T62: Indirect procurement iPRO, Professional services, Patent services | U62: Indirect procurement iPRO, Professional services, Patent services | X62: Net 45 days | AK62: 506965
B63: Aalto University Executive Education Oy | C63: Aalto University Executive Education Oy | D63: HELSINKI | E63: Finland | G63: Active | I63: 37918.661 | K63: 20196 | M63: 615149 | N63: =VLOOKUP(M63,'Spend Export'!$B:$E,4,FALSE) -> 220586.65 | P63: FI05909643 | R63: No | S63: Yes | T63: Indirect procurement iPRO, Personnel, Training & people development | U63: Indirect procurement iPRO, Personnel, Training & people development | V63: Carnicelli Laura | W63: laura.carnicelli@aaltoee.fi | X63: Net 45 days | AH63: Korpela Tuija | AK63: 615149
B64: KWSOFT - Krzysztof Juskiewicz | C64: KWSOFT - Krzysztof Juskiewicz | D64: PLESZEW | E64: Poland | G64: Active | I64: 44571.531 | J64: Mähönen-Mendoza Emma | K64: 303504 | M64: 647353 | N64: =VLOOKUP(M64,'Spend Export'!$B:$E,4,FALSE) -> #N/A | P64: PL6171510685 | R64: No | S64: Yes | T64: Indirect procurement iPRO, Office IT, IT consulting;Indirect procurement iPRO, Professional services, Business consulting | U64: Indirect procurement iPRO, Office IT, IT consulting | V64: Juśkiewicz Krzysztof | W64: krzysztof.juskiewicz@kwsoft.com.pl | X64: Net 30 days | Y64: X | AA64: Mähönen-Mendoza Emma | AG64: Mölsä Annemari | AI64: 2022-01-10 1001 - Infor LN (COF) (Valmet), Indirect procurement iPRO, Professional services, Business consulting accepted by Mäkelä Henri | AK64: 647353
B65: Kilmantec Oy | C65: Kilmantec Oy | D65: LAHTI | E65: Finland | G65: Active | I65: 37918.677 | K65: 21482 | L65: 368715699 | M65: 605007 | N65: =VLOOKUP(M65,'Spend Export'!$B:$E,4,FALSE) -> #N/A | P65: FI14746284 | R65: No | S65: Yes | T65: Indirect procurement iPRO, Office IT, IT consulting | U65: Indirect procurement iPRO, Office IT, IT consulting | V65: Minkkinen Juha | W65: juha.minkkinen@valmetpartners.com | X65: Net 30 days | AK65: 605007
B66: Infor (Sweden) AB | C66: Infor (Sweden) AB | D66: KISTA | E66: Sweden | G66: Active | I66: 41808.361 | K66: 226477 | M66: 381373 | N66: =VLOOKUP(M66,'Spend Export'!$B:$E,4,FALSE) -> #N/A | P66: SE556224134801 | R66: No | S66: Yes | T66: Indirect procurement iPRO, Office IT, IT consulting | U66: Indirect procurement iPRO, Office IT, IT consulting | V66: Delies Caroline | W66: caroline.delies@infor.com | X66: Net 45 days | AK66: 381373
A67: Åbo Akademi | B67: Åbo Akademi | C67: Åbo Akademi | D67: TURKU | E67: Finland | G67: Active | H67: C3 | I67: 37918.953 | K67: 37555 | L67: 368905167 | M67: 603992 | N67: =VLOOKUP(M67,'Spend Export'!$B:$E,4,FALSE) -> 212402.74 | P67: FI02463121 | R67: Yes | S67: Yes | T67: Indirect procurement iPRO, Marketing & communication, Membership & association fees;Indirect procurement iPRO, Professional services;Indirect procurement iPRO, Professional services, R&D services & materials;Indirect procurement iPRO, Professional services, Testing, measurement & inspection;Services, R&D engineering | U67: Indirect procurement iPRO, Professional services, R&D services & materials | V67: Xu Chunlin | W67: chunlin.xu@abo.fi | X67: Net 14 days | Y67: X | Z67: X | AG67: INACTIVE Koskinen Tero | AI67: 2023-01-24 1001 - Infor LN (PAP), Indirect procurement iPRO, Professional services, Testing, measurement & inspection accepted by Snedsböl Truls | AK67: 603992
B68: Ples Florin | C68: Ples Florin | D68: PERGINE VALSUGANA | E68: Italy | F68: florinpit@yahoo.it | G68: Active | I68: 43474.715 | J68: INACTIVE Nevalainen Merja H | K68: 289220 | M68: 649340 | N68: =VLOOKUP(M68,'Spend Export'!$B:$E,4,FALSE) -> #N/A | P68: IT02664950223 | R68: No | S68: Yes | T68: Indirect procurement iPRO, Office IT, IT consulting | U68: Indirect procurement iPRO, Office IT, IT consulting | V68: Ples Florin | W68: florin.ples@valmetpartners.com | X68: Net 14 days | Y68: X | Z68: X | AA68: Mähönen-Mendoza Emma;Ndiritu Grace | AI68: 2019-01-10 639 - Valmet Technologies, Inc PPP HO (MP) (Valmet), Indirect procurement iPRO, Office IT, IT consulting (Main category) accepted by INACTIVE Vaiste Ismo | AK68: 628153
B69: Zeal Sourcing Oy | C69: Zeal Sourcing Oy | D69: HELSINKI | E69: Finland | G69: Active | I69: 44936.355 | J69: Liukkonen Marko | K69: 311341 | M69: 657766 | N69: =VLOOKUP(M69,'Spend Export'!$B:$E,4,FALSE) -> #N/A | P69: FI31280017 | R69: No | S69: Yes | T69: Indirect procurement iPRO, Office IT, IT consulting;Indirect procurement iPRO, Professional services, Business consulting | U69: Indirect procurement iPRO, Office IT, IT consulting | V69: Suorsa Antti | W69: antti@zealsourcing.fi | X69: Net 30 days | AA69: INACTIVE Sjöborg Jens | AI69: 2023-01-10 1001 - Infor LN (COF) (Valmet), Indirect procurement iPRO, Professional services, Business consulting accepted by Snedsböl Truls | AK69: 657766
B70: Share2Learn S.L. | C70: Share2Learn S.L. | D70: MADRID | E70: Spain | G70: Active | I70: 44617.394 | J70: INACTIVE Pöyhtäri Jukka-Pekka | K70: 304189 | M70: 648343 | N70: =VLOOKUP(M70,'Spend Export'!$B:$E,4,FALSE) -> 205741.39 | P70: ESB39861562 | R70: Yes | S70: Yes | T70: Indirect procurement iPRO, Professional services, Business consulting | U70: Indirect procurement iPRO, Professional services, Business consulting | V70: Gutierrez Helena | W70: helena.gutierrez@shareplm.com | X70: Net 30 days | Y70: X | AB70: Ottosson Magdalena | AI70: 2022-02-28 1001 - Infor LN (PAP), Indirect procurement iPRO, Professional services, Business consulting (Main category) accepted by Mäkelä Henri | AK70: 648343
B71: Purmaconsulting Oy | C71: Purmaconsulting Oy | D71: LEMPÄÄLÄ | E71: Finland | F71: purmaconsulting@gmail.com | G71: Active | I71: 41501.54 | K71: 222048 | M71: 375834 | N71: =VLOOKUP(M71,'Spend Export'!$B:$E,4,FALSE) -> #N/A | P71: FI25617584 | R71: No | S71: Yes | T71: Indirect procurement iPRO, Office IT, IT consulting | U71: Indirect procurement iPRO, Office IT, IT consulting | V71: Purma | W71: lasse.purma@purmaconsulting.com | X71: Net 45 days | Y71: X | AA71: Liukkonen Marko;Korhonen Pauli | AK71: 375834
B72: Cloud2 Oy | C72: Cloud2 Oy | D72: HELSINKI | E72: Finland | G72: Active | I72: 44685.644 | J72: Liukkonen Marko | K72: 305125 | M72: 649380 | N72: =VLOOKUP(M72,'Spend Export'!$B:$E,4,FALSE) -> #N/A | P72: FI28325907 | R72: No | S72: Yes | T72: Indirect procurement iPRO, Office IT, IT consulting | U72: Indirect procurement iPRO, Office IT, IT consulting | V72: Oksanen Saku | W72: saku.oksanen@cloud2.fi | X72: Net 60 days | Y72: X | Z72: X | AA72: Liukkonen Marko;Burmeister Jari | AI72: 2022-05-23 1001 - Infor LN (PAP), Indirect procurement iPRO, Office IT, IT consulting (Main category) accepted by Tapiola Mika | AK72: 649380
B73: Roschier Asianajotoimisto Oy | C73: Roschier Asianajotoimisto Oy | D73: HELSINKI | E73: Finland | G73: Active | I73: 37928.619 | K73: 40066 | M73: 163166 | N73: =VLOOKUP(M73,'Spend Export'!$B:$E,4,FALSE) -> 199644.11 | P73: FI92093629 | R73: No | S73: Yes | T73: Indirect procurement iPRO, Professional services, Legal services | U73: Indirect procurement iPRO, Professional services, Legal services | V73: Sidklev Johan | W73: johan.sidklev@roschier.com | X73: Net 30 days | Z73: X | AK73: 163166
B74: Reinhart Boerner Van Deuren S.C. | C74: Reinhart Boerner Van Deuren S.C. | D74: MILWAUKEE | E74: United States | G74: Active | I74: 39469.97 | K74: 118645 | M74: 255408 | N74: =VLOOKUP(M74,'Spend Export'!$B:$E,4,FALSE) -> 196242.66 | R74: No | S74: Yes | T74: Indirect procurement iPRO, Professional services, Legal services | U74: Indirect procurement iPRO, Professional services, Legal services | X74: Net 30 days | AI74: 2018-10-30 1001 - Infor LN (SER), Indirect procurement iPRO, Professional services, Legal services (Main category) accepted by Mäkelä Henri | AK74: 255408
B75: Digital Workforce Services Oy | C75: Digital Workforce Services Oy | D75: HELSINKI | E75: Finland | F75: info@digitalworkforce.fi | G75: Active | I75: 43080.529 | J75: INACTIVE Länsimies Jukka | K75: 284709 | M75: 622218 | N75: =VLOOKUP(M75,'Spend Export'!$B:$E,4,FALSE) -> #N/A | P75: FI27047925 | R75: No | S75: Yes | T75: Indirect procurement iPRO, Office IT, IT consulting;Indirect procurement iPRO, Office IT, Software licenses, IT consulting | U75: Indirect procurement iPRO, Office IT, Software licenses, IT consulting | V75: Närhi Jenni | W75: jenni.narhi@digitalworkforce.com | X75: Net 30 days | Z75: X | AA75: Liukkonen Marko;Frisk Sami | AI75: 2023-08-03 FC - Infor M3 (FC) (FC), Indirect procurement iPRO, Office IT, IT consulting accepted by Tapiola Mika | AK75: 622218
B76: LRQA Limited, Suomen sivuliike | C76: LRQA Limited, Suomen sivuliike | D76: HELSINKI | E76: Finland | G76: Active | I76: 40227.511 | K76: 148854 | M76: 292268 | N76: =VLOOKUP(M76,'Spend Export'!$B:$E,4,FALSE) -> 188141.16 | P76: FI23034385 | Q76: X | R76: No | S76: Yes | T76: Indirect procurement iPRO, Professional services, Certification, standardization & audits | U76: Indirect procurement iPRO, Professional services, Certification, standardization & audits | V76: Hujanen Jukka | W76: jukka.hujanen@lr.org | X76: Net 60 days | Z76: X | AH76: Snedsböl Truls | AI76: 2021-03-16 1001 - Infor LN (COF) (Valmet), Indirect procurement iPRO, Professional services, Certification, standardization & audits (Main category) accepted by INACTIVE Heikkinen Joona Kalle Matias | AK76: 292268
B77: Genpact (Uk) Limited | C77: Genpact (Uk) Limited | D77: LONDON | E77: United Kingdom | G77: Active | I77: 44706.313 | J77: Virnes Markku | K77: 305158 | M77: 649721 | N77: =VLOOKUP(M77,'Spend Export'!$B:$E,4,FALSE) -> #N/A | P77: GB849126115 | R77: No | S77: Yes | T77: Indirect procurement iPRO, Office IT, IT consulting | U77: Indirect procurement iPRO, Office IT, IT consulting | V77: Lundström Irene | W77: irene.lundstrom@genpact.com | X77: Net 30 days | AA77: Tapiola Mika;Liukkonen Marko;Wilén Anni | AI77: 2022-05-25 Indirect procurement iPRO, Office IT, IT consulting (Main category) accepted by | AK77: 649721
B78: TMI Frank Torres | C78: TMI Frank Torres | D78: HELSINKI | E78: Finland | F78: frankjt@netcabo.pt | G78: Active | I78: 43474.73 | J78: INACTIVE Nevalainen Merja H | K78: 289219 | M78: 628154 | N78: =VLOOKUP(M78,'Spend Export'!$B:$E,4,FALSE) -> #N/A | P78: FI28394777 | R78: No | S78: Yes | T78: Indirect procurement iPRO, Office IT, IT consulting | U78: Indirect procurement iPRO, Office IT, IT consulting | V78: Torres Frank | W78: frank.torres@valmetpartners.com | X78: Net 14 days | Y78: X | Z78: X | AG78: Ndiritu Grace | AI78: 2019-01-10 639 - Valmet Technologies, Inc PPP HO (MP) (Valmet), Indirect procurement iPRO, Office IT, IT consulting (Main category) accepted by INACTIVE Vaiste Ismo | AK78: 628154
B79: Teknologian tutkimuskeskus VTT Oy | C79: VTT Konsernitoiminnot | D79: ESPOO | E79: Finland | G79: Active | I79: 37918.944 | K79: 37156 | L79: 368919580 | M79: 618089 | N79: =VLOOKUP(M79,'Spend Export'!$B:$E,4,FALSE) -> 175534.61 | P79: FI26473754 | R79: Yes | S79: Yes | T79: Indirect procurement iPRO, Professional services;Indirect procurement iPRO, Professional services, R&D services & materials | U79: Indirect procurement iPRO, Professional services, R&D services & materials | V79: Kuusisaari Jaakko | W79: jaakko.kuusisaari@vtt.fi | X79: Net 45 days | Z79: X | AG79: INACTIVE Meroma Outi | AI79: 2015-11-26 634 - Valmet Technologies, Inc FIB Pori (MP) (P&E), Indirect procurement iPRO, Professional services accepted by Loikkanen Janne | AK79: 618089
B80: Verona Consulting Oy | C80: Verona Consulting Oy | D80: HELSINKI | E80: Finland | F80: info@veronaconsulting.fi | G80: Active | I80: 37918.87 | K80: 33542 | L80: 369404327 | M80: 606814 | N80: =VLOOKUP(M80,'Spend Export'!$B:$E,4,FALSE) -> 174322.44 | P80: FI15999793 | R80: No | S80: Yes | T80: Indirect procurement iPRO, Personnel, Training & people development | U80: Indirect procurement iPRO, Personnel, Training & people development | V80: Pennanen Risto | W80: risto.pennanen@verona.fi | X80: Net 45 days | AK80: 606814
B81: Comion Oy | C81: Comion Oy | D81: TAMPERE | E81: Finland | G81: Active | I81: 41514.635 | K81: 222332 | M81: 376161 | N81: =VLOOKUP(M81,'Spend Export'!$B:$E,4,FALSE) -> #N/A | P81: FI25602075 | R81: No | S81: Yes | T81: Indirect procurement iPRO, Office IT, IT consulting;Indirect procurement iPRO, Professional services, R&D services & materials;Services, Automation engineering, Automation engineering | U81: Indirect procurement iPRO, Office IT, IT consulting | V81: Mikkola Pekka | W81: pekka.mikkola@comion.fi | X81: Net 30 days | Z81: X | AA81: Tapiola Mika;Liukkonen Marko | AK81: 376161
B82: Navcite Consulting AB | C82: Navcite Consulting AB | D82: LULEÅ | E82: Sweden | F82: support@navcite.se | G82: Active | I82: 40002.621 | K82: 139344 | M82: 280824 | N82: =VLOOKUP(M82,'Spend Export'!$B:$E,4,FALSE) -> #N/A | P82: SE556758541801 | R82: No | S82: Yes | T82: Indirect procurement iPRO, Office IT, IT consulting | U82: Indirect procurement iPRO, Office IT, IT consulting | V82: support | W82: support@navcite.se | X82: Net 60 days | Y82: X | AA82: Tapiola Mika | AK82: 280824
B83: T&m Consultoria Empresarial LTDA | C83: T&m Consultoria Empresarial LTDA | D83: GOIÂNIA | E83: Brazil | G83: Active | I83: 44064.629 | J83: Toropainen Anita | K83: 297167 | M83: 638581 | N83: =VLOOKUP(M83,'Spend Export'!$B:$E,4,FALSE) -> #N/A | R83: No | S83: Yes | T83: Indirect procurement iPRO, Office IT, IT consulting | U83: Indirect procurement iPRO, Office IT, IT consulting | V83: Muller Joao | W83: joao.g.muller@gmail.com | X83: Net 45 days | Z83: X | AG83: Mähönen-Mendoza Emma | AI83: 2020-09-03 1001 - Infor LN (PAP), Indirect procurement iPRO, Office IT, IT consulting (Main category) accepted by Tapiola Mika | AK83: 638581
B84: Needexperts SAS | C84: Needexperts SAS | D84: LINGOLSHEIM | E84: France | G84: Active | I84: 42128.448 | K84: 230607 | M84: 385972 | N84: =VLOOKUP(M84,'Spend Export'!$B:$E,4,FALSE) -> #N/A | P84: FR54799554621 | R84: No | S84: Yes | T84: Indirect procurement iPRO, Office IT, IT consulting | U84: Indirect procurement iPRO, Office IT, IT consulting | X84: Net 30 days | AK84: 385972
B85: E & P Import Oy | C85: E & P Import Oy | D85: RAUTALAMPI | E85: Finland | G85: Active | I85: 44804.426 | J85: Malinen Mervi | K85: 306275 | M85: 651510 | N85: =VLOOKUP(M85,'Spend Export'!$B:$E,4,FALSE) -> #N/A | R85: No | S85: Yes | T85: Indirect procurement iPRO, Office IT, IT consulting | U85: Indirect procurement iPRO, Office IT, IT consulting | V85: Pesonen Kalle | W85: kallepesone@gmail.com | X85: Net 30 days | Y85: X | Z85: X | AA85: Liukkonen Marko;INACTIVE Tolonen Arto | AI85: 2022-09-01 1001 - Infor LN (COF) (Valmet), Indirect procurement iPRO, Office IT, IT consulting (Main category) accepted by Tapiola Mika | AK85: 651510
B86: Nice-business Consulting Oy | C86: Nice-business Consulting Oy | D86: HELSINKI | E86: Finland | G86: Active | I86: 44603.435 | J86: Virnes Markku | K86: 304029 | M86: 648152 | N86: =VLOOKUP(M86,'Spend Export'!$B:$E,4,FALSE) -> #N/A | P86: FI15780599 | R86: No | S86: Yes | T86: Indirect procurement iPRO, Office IT, IT consulting | U86: Indirect procurement iPRO, Office IT, IT consulting | V86: Antila Tarmo | W86: tarmo.antila@fujitsu.com | X86: Net 60 days | Y86: X | Z86: X | AA86: Tapiola Mika;Liukkonen Marko;Soikkanen Sirpa | AI86: 2022-02-11 Indirect procurement iPRO, Office IT, IT consulting (Main category) accepted by | AK86: 648152
B87: Kova PMC Oy | C87: Kova PMC Oy | D87: LAPUA | E87: Finland | G87: Active | I87: 43896.416 | J87: Hakanen Tytti | K87: 294439 | M87: 635184 | N87: =VLOOKUP(M87,'Spend Export'!$B:$E,4,FALSE) -> 157288.23 | P87: FI29944398 | R87: No | S87: Yes | T87: Indirect procurement iPRO, Professional services, Business consulting | U87: Indirect procurement iPRO, Professional services, Business consulting | V87: Kivisalo Sami | W87: sami.kivisalo@kovaholding.fi | X87: Net 45 days | AG87: Lestelin Pasi | AI87: 2020-03-10 210 - Valmet Power Finland (POWFIN) (P&E), Indirect procurement iPRO, Professional services, Business consulting (Main category) accepted by Mäkelä Henri | AK87: 635184
B88: Sphera Solutions, Inc., | C88: Sphera Solutions, Inc., | D88: CHICAGO | E88: United States | G88: Active | I88: 43817.637 | J88: Soikkanen Sirpa | K88: 293228 | M88: 633603 | N88: =VLOOKUP(M88,'Spend Export'!$B:$E,4,FALSE) -> #N/A | R88: No | S88: Yes | T88: Indirect procurement iPRO, Office IT, IT consulting | U88: Indirect procurement iPRO, Office IT, IT consulting | V88: Sinkinson James | W88: jsinkinson@sphera.com | X88: Net 45 days | Z88: X | AI88: 2020-01-02 1001 - Infor LN (COF) (Valmet), Indirect procurement iPRO, Office IT, IT consulting (Main category) accepted by Tapiola Mika | AK88: 633603
B89: Elisa IndustrIQ Finland Oy | C89: Elisa IndustrIQ Finland Oy | D89: TAMPERE | E89: Finland | G89: Active | I89: 43837.618 | J89: Laitiainen Outi | K89: 295050 | M89: 633834 | N89: =VLOOKUP(M89,'Spend Export'!$B:$E,4,FALSE) -> #N/A | P89: FI25313679 | R89: Yes | S89: Yes | T89: Indirect procurement iPRO, Office IT, IT consulting | U89: Indirect procurement iPRO, Office IT, IT consulting | V89: Julmala Harri | W89: harri.julmala@leanware.fi | X89: Net 60 days | Z89: X | AI89: 2020-05-14 1001 - Infor LN (SER), Indirect procurement iPRO, Office IT, IT consulting (Main category) accepted by Tapiola Mika | AK89: 633834
A90: Deloitte | B90: Deloitte Consulting Oy | C90: Deloitte Consulting Oy | D90: HELSINKI | E90: Finland | G90: Active | H90: C3 | I90: 38708.501 | K90: 92459 | M90: 224402 | N90: =VLOOKUP(M90,'Spend Export'!$B:$E,4,FALSE) -> 152103.03 | P90: FI05553456 | R90: No | S90: Yes | T90: Indirect procurement iPRO, Professional services, Business consulting | U90: Indirect procurement iPRO, Professional services, Business consulting | V90: Huttu Essi | W90: Essi.Huttu@deloitte.fi | X90: Net 14 days | Z90: X | AG90: Saari Mika | AH90: Snedsböl Truls | AK90: 224402
B91: Hannes Snellman Advokatbyrå Ab | C91: Hannes Snellman Advokatbyrå Ab | D91: HELSINKI | E91: Finland | F91: hannes.snellman@hannessnellman.com | G91: Active | I91: 37928.58 | K91: 38328 | M91: 161306 | N91: =VLOOKUP(M91,'Spend Export'!$B:$E,4,FALSE) -> 147726.81 | P91: FI92093637 | R91: No | S91: Yes | T91: Indirect procurement iPRO, Professional services, Legal services | U91: Indirect procurement iPRO, Professional services, Legal services | V91: Aalto Johan | W91: johan.aalto@hannessnellman.com | X91: Net 45 days | AH91: Snedsböl Truls | AK91: 161306
B92: CPQ Finland Oy | C92: CPQ Finland Oy | D92: PORVOO | E92: Finland | F92: vmm@cpqfinland.fi | G92: Active | I92: 43052.601 | J92: INACTIVE Taivassalo Milja | K92: 284336 | M92: 625641 | N92: =VLOOKUP(M92,'Spend Export'!$B:$E,4,FALSE) -> #N/A | P92: FI29205173 | R92: Yes | S92: Yes | T92: Indirect procurement iPRO, Office IT, IT consulting | U92: Indirect procurement iPRO, Office IT, IT consulting | V92: Myllymäki Veli-Matti | W92: vmm@cpqfinland.fi | X92: Net 30 days | Z92: X | AI92: 2017-11-14 636 - Valmet Technologies, Inc MIL PER (MP) (SER), Indirect procurement iPRO, Office IT, IT consulting (Main category) accepted by INACTIVE Vaiste Ismo | AK92: 621732
B93: EY Advisory Oy | C93: EY Advisory Oy | D93: HELSINKI | E93: Finland | G93: Active | I93: 44862.454 | J93: Helminen Päivi | K93: 310479 | M93: 656278 | N93: =VLOOKUP(M93,'Spend Export'!$B:$E,4,FALSE) -> 144300.86 | P93: FI32837059 | R93: Yes | S93: Yes | T93: Indirect procurement iPRO, Professional services, Business consulting | U93: Indirect procurement iPRO, Professional services, Business consulting | V93: Äijälä Mikko | W93: mikko.aijala@fi.ey.com | X93: Net 60 days | AG93: INACTIVE Vajavaara Heikki | AI93: 2024-09-11 359 - Vietnam Baan (SER), Indirect procurement iPRO, Professional services, Business consulting accepted by Phulphiphat Usa | AK93: 656278
B94: Nortal Oy | C94: Nortal Oy | D94: HELSINKI | E94: Finland | F94: Accounts.Receivable@ccc.fi | G94: Active | I94: 37918.58 | J94: INACTIVE Honkanen Jani | K94: 12235 | M94: 509192 | N94: =VLOOKUP(M94,'Spend Export'!$B:$E,4,FALSE) -> #N/A | P94: FI07281351 | R94: No | S94: Yes | T94: Indirect procurement iPRO, Office IT, IT consulting | U94: Indirect procurement iPRO, Office IT, IT consulting | V94: Rönkkö Petri | W94: Petri.Ronkko@nortal.com | X94: Net 45 days | Y94: X | Z94: X | AA94: INACTIVE Honkanen Jani | AI94: 2021-06-22 1001 - Infor LN (COF) (Valmet), Indirect procurement iPRO, Office IT, IT consulting (Main category) accepted by Tapiola Mika | AK94: 509192
B95: Mazeppa Danmark ApS | C95: Mazeppa Danmark ApS | D95: ODENSE C | E95: Denmark | G95: Active | I95: 44733.583 | J95: Latini Luca | K95: 305689 | M95: 650316 | N95: =VLOOKUP(M95,'Spend Export'!$B:$E,4,FALSE) -> #N/A | P95: DK33149034 | R95: No | S95: Yes | T95: Indirect procurement iPRO, Office IT, IT consulting;Indirect procurement iPRO, Professional services, Business consulting | U95: Indirect procurement iPRO, Office IT, IT consulting | V95: Gierahn Christian | W95: christian.gierahn@mazeppagroup.com | X95: Net 45 days | AI95: 2022-06-23 1001 - Infor LN (COF) (Valmet), Indirect procurement iPRO, Professional services, Business consulting accepted by Mäkelä Henri | AK95: 650316
B96: Ceili Oy | C96: Ceili Oy | D96: JYVÄSKYLÄ | E96: Finland | G96: Active | I96: 43584.783 | J96: Borel Xavier | K96: 244273 | M96: 629830 | N96: =VLOOKUP(M96,'Spend Export'!$B:$E,4,FALSE) -> #N/A | P96: FI29853146 | R96: No | S96: Yes | T96: Components and equipment, IT components, Other IT components;Indirect procurement iPRO, Marketing & communication, Advertising & branding;Indirect procurement iPRO, Office IT, IT consulting | U96: Indirect procurement iPRO, Office IT, IT consulting | V96: Freyberg Kivikari | W96: kivikari.freyberg@ceili.fi | X96: Net 45 days | Z96: X | AA96: Borel Xavier;Tapiola Mika;Liukkonen Marko | AI96: 2020-12-23 304 - LAE Production T3.4 (LAE) (SER), Indirect procurement iPRO, Marketing & communication, Advertising & branding accepted by Monprasit Kobporn | AK96: 629830
B97: Tiedtke-Bühling-Kinne & Partner GbR | C97: Tiedtke-Bühling-Kinne & Partner GbR | D97: MUNICH | E97: Germany | F97: postoffice@tbk-patent.de | G97: Active | I97: 37918.89 | K97: 34517 | M97: 603165 | N97: =VLOOKUP(M97,'Spend Export'!$B:$E,4,FALSE) -> 138821.12 | P97: DE130748035 | R97: No | S97: Yes | T97: Indirect procurement iPRO, Professional services, Patent services | U97: Indirect procurement iPRO, Professional services, Patent services | V97: TBK Info | W97: tbkpost@tbk.com | X97: Net 30 days | AK97: 603165
B98: Centroid Consulting LLC | C98: Centroid Consulting LLC | D98: TROY | E98: United States | G98: Active | I98: 44663.682 | J98: Virnes Markku | K98: 304698 | M98: 649080 | N98: =VLOOKUP(M98,'Spend Export'!$B:$E,4,FALSE) -> #N/A | R98: No | S98: Yes | T98: Indirect procurement iPRO, Office IT, IT consulting | U98: Indirect procurement iPRO, Office IT, IT consulting | V98: Info | W98: info@centroid.com | X98: Net 30 days | AA98: Tapiola Mika | AI98: 2022-04-12 Indirect procurement iPRO, Office IT, IT consulting (Main category) accepted by | AK98: 649080
B99: Integrity Consulting Oy | C99: Integrity Consulting Oy | D99: ESPOO | E99: Finland | G99: Active | I99: 44603.435 | J99: Virnes Markku | K99: 304030 | M99: 648153 | N99: =VLOOKUP(M99,'Spend Export'!$B:$E,4,FALSE) -> #N/A | P99: FI29062387 | R99: No | S99: Yes | T99: Indirect procurement iPRO, Office IT, IT consulting | U99: Indirect procurement iPRO, Office IT, IT consulting | V99: Nambiar Diresh | W99: diresh.nambiar@gmail.com | X99: Net 30 days | Y99: X | AA99: Tapiola Mika | AI99: 2022-02-11 Indirect procurement iPRO, Office IT, IT consulting (Main category) accepted by | AK99: 648153
B100: Board of Innovation BVBA | C100: Board of Innovation BVBA | D100: ANTWERP | E100: Belgium | G100: Active | I100: 42930.446 | K100: 249803 | M100: 406951 | N100: =VLOOKUP(M100,'Spend Export'!$B:$E,4,FALSE) -> 135525.68 | P100: BE0818009314 | R100: No | S100: Yes | T100: Indirect procurement iPRO, Personnel, Training & people development | U100: Indirect procurement iPRO, Personnel, Training & people development | X100: Net 45 days | AK100: 406951
...

Sheet FI_dataPOCcleaned
A1: This sheet has illustrative detail on Training category suppliers that has been collected by category manager but is not available in supplier master fully
A3: Business Partner Company Name | B3: Supplier code | C3: Training supplier Y/N | D3: EXAMPLES: Pricing / day / trainer EUR (if no data: average based on invoicing) | E3: Country | F3: Delivery country | G3: Contract available at the moment | H3: Classification | I3: Nature of the service | J3: Training area | K3: HSE training provider | L3: Valmet contact person (CoMPass) | M3: Catalog in Basware Shop | N3: Preferred supplier in CoMPass (Mikko)
A4: IMD-International Institute for Managem. Develop. | B4: 383390 | C4: Y | D4: no detailed info | E4: Finland | F4: Global | G4: Y | H4: A | I4: Global training programs | J4: Global training programs / Forward | L4: Tuija Korpela, Hanna Heikkilä | M4: y
A5: Aalto University Executive Education Oy | B5: 615149 | C5: Y | D5: no detailed info | E5: Finland | F5: Global | G5: Y | H5: A | I5: Leadership, management and team development | J5: World Class Supply chain, Global leader, First time manager, CSRD & sustainability reporting, MBA | L5: Tuija Korpela, Riikka Happonen | M5: y
A6: AS3 Finland Oy | B6: 403389 | C6: Y | D6: 3000 | E6: Finland | F6: Global | G6: Y | H6: A | I6: Coaching and work counseling | J6: Group coaching new managers, coaching, manager as career coach training | L6: Tuija Korpela | M6: y | N6: Yes
A7: Hanken & SSE Executive Education Ab | B7: 288703 | C7: Y | D7: no detailed info | E7: Finland | F7: Global | G7: Y | H7: A | I7: Leadership, management and team development | J7: Hanken EMBA programme fees | L7: Jussi Mäntyniemi | M7: y
A8: IMPLEMENT CONSULTING GROUP P/S | B8: 391772 | C8: Y | D8: no detailed info | E8: Finland | F8: Global | G8: Y | H8: A | I8: HSE, quality and work wellbeing | J8: Leading through lean | K8: x | L8: Meri-Tuuli Sipari | M8: y
A9: Bitville Oy | B9: 400676 | C9: Y | D9: no detailed info | E9: Finland | G9: N | H9: A
A10: Resilio Oy | B10: 407540 | C10: Y | D10: 2000 | E10: Finland | F10: Finland / EMEA | G10: Y | H10: A | I10: HSE, quality and work wellbeing +J7:J10 | J10: Work psychologist services most part, Manager guidance | K10: x | L10: Tuija Korpela, Anne Onkila | M10: y | N10: Yes
A11: Peili Consulting Oy | B11: 386353 | C11: Y | D11: 2000 | E11: Finland | F11: Global | G11: Y | H11: A | I11: Interaction/ presentation/ communication/ influencing | J11: Peili -trainings | L11: Reijo Heinämäki | M11: y | N11: Yes
A12: Hope Consulting Oy | B12: 389324 | C12: Y | D12: 2500 | E12: Finland | F12: Finland | G12: Y | H12: A | I12: Coaching and work counseling | J12: Work counselling of a new manager | L12: Tuija Korpela, Eero Halmari | M12: y | N12: Yes
A13: Medwick V. Byrd Jr. | B13: 601076 | C13: Y | D13: 1200 | E13: Finland | F13: Global | G13: Y | H13: A | I13: Product, service or technology trainings | J13: Valmet Process Technology School training | L13: Reijo Heinämäki | M13: y
A14: Pal Lokendra | B14: 622308 | C14: Y | D14: 1200 | E14: Finland | F14: Global | G14: Y | H14: A | I14: Product, service or technology trainings | J14: Valmet Process Technology School | L14: Reijo Heinämäki | M14: y
A15: EF Corporate Education Ltd | B15: 665822 | C15: Y | D15: no detailed info | E15: Finland | G15: Y | H15: A | I15: Business culture and language training | J15: language training | L15: Jutta Rouru | M15: y
A16: International Institute for Learning Finland Oy | B16: 295648 | C16: Y | D16: 2500 | E16: Finland | F16: Global | G16: Y | H16: A | I16: Leadership, management and team development, project management | J16: PMIQ, Agile & scrum, PMI Authorized PMP | L16: Eero Halmari | M16: y
A17: Hasan Jameel | B17: 601536 | C17: Y | D17: 1300 | E17: Finland | F17: Global | G17: Y | H17: A | I17: Product, service or technology trainings | J17: Valmet Process Technology School training | L17: Reijo Heinämäki | M17: y
A18: Verona Consulting Oy | B18: 606814 | C18: Y | D18: no detailed info | E18: Finland | F18: Global | G18: Y | H18: A | I18: Global training programs | J18: Champions in Services | L18: Riikka Happonen | M18: y
A19: Board of Innovation BVBA | B19: 406951 | C19: Y | D19: no detailed info | E19: Finland | F19: Global | G19: Y | H19: A | I19: Global training programs | J19: Enhanced IP 2023 project | L19: Riikka Happonen | M19: y
A20: Hyvinvoinnin Suurlähettiläät Oy | B20: 635292 | C20: Y | D20: 4000 | E20: Finland | F20: EMEA | G20: Y | H20: A | I20: Leadership, management and team development | J20: Training site leaders, co-operation development process, leadership team development process 360, Coaching training for managers | L20: Eero Halmari
A21: Anna-Mari Laulumaa Oy | B21: 240448 | C21: Y | E21: Finland | G21: N | H21: B | I21: Business culture and language training | J21: Interaction training | L21: Tuomo Linnaranta
A22: Sinkkonen Consulting Oy | B22: 349102 | C22: Y | E22: Finland | F22: EMEA | G22: Y | H22: B | I22: Business culture and language training | J22: Global moblity related trainings, for expatriates etc, | L22: Riikka Hermunen
A23: AEL-Amiedu Oy | B23: 634973 | C23: Y | E23: Finland | F23: Finland | G23: N | H23: B | I23: Product, service or technology trainings | J23: Technical training | L23: Jyri Palmu
A24: Helsingin Kamari Oy | B24: 509013 | C24: Y | E24: Finland | F24: Finland | G24: Under negotiation | H24: B | I24: Various/other skills | J24: User licenses and brand visibility, few export trainings, Koulutus-Online platform | L24: Ari Leppäniemi
A25: Saranen Consulting Oy | B25: 389430 | C25: Y | E25: Finland | F25: Finland | G25: N | H25: B | I25: Product, service or technology trainings | J25: Participation in training program: Industry 4.0 and automation; Outplacement services | L25: Petra Miesmaa
A26: Tampere Business Campus TBC ry | B26: 224445 | C26: Y | E26: Finland | F26: Finland | G26: N | H26: B | I26: Various/other skills | J26: TBC licence, fees for late cancellation of event participation | L26: Jenni Siivonen
A27: Jyväskylän Ammattikorkeakoulu | B27: 201515 | C27: Y | E27: Finland | F27: Finland | G27: Y | H27: B | I27: Various/other skills | J27: E-learning services, Co-operation agreement 3 years finance and business law students, Equiqment calibration, another co-operation agreement with student union | L27: Reijo Heinämäki
A28: Apprix Oy | B28: 239755 | C28: Y | E28: Finland | F28: Finland | G28: Y | H28: B | I28: Elearnings and digital learning solutions | J28: Builder user license monthly, project work related to e-learning courses | L28: Meri-Tuuli Sipari
A29: Psykologipalvelut Hippu Pintilä | B29: 635240 | C29: Y | E29: Finland | F29: Finland | G29: N | H29: B | I29: Leadership, management and team development; HSE, quality and work wellbeing | J29: Management team development, work guidance for managers, team development, Discovery insights , workshops | K29: x | L29: Eero Halmari
A30: North Carolina State University | B30: 601852 | C30: Y | E30: Finland | F30: Global | G30: Y | H30: B | I30: Product, service or technology trainings | J30: Can't access information | L30: Niklas Nylund
A31: Jyväskylän Yliopisto | B31: 224515 | C31: Y | E31: Finland | F31: Finland / Global | G31: N | H31: B | I31: Various/other skills | J31: Printing costs for masters thesis | L31: Miia Lompolo
A32: Rokmind Oy | B32: 647801 | C32: Y | E32: Finland | F32: Finland | G32: N | H32: B | I32: Leadership, management and team development | J32: Services: Insight Profiles for IT Leap (Team development assessments) | L32: Eero Halmari
A33: Nordic Business Forum Oy | B33: 657108 | C33: N | E33: Finland | F33: Global | G33: N | H33: B | I33: Leadership, management and team development | J33: NBF Remote license | L33: Mika Tapiola
A34: Kaakkois-Suomen Ammattikorkeakoulu Oy | B34: 623267 | C34: Y | E34: Finland | G34: N | H34: B | I34: Various/other skills | J34: NextGenMix-project | L34: Reijo Pietikäinen
A35: Oy Speakers Forum Finland Ab | B35: 331659 | C35: N | E35: Finland | G35: N | H35: B | I35: HSE, quality and work wellbeing | J35: Karri Kivi, tyhy-speaker | K35: x | L35: Eero Halmari
A36: Itä-Suomen Yliopisto | B36: 291786 | E36: Finland | G36: N | H36: B | I36: Various/other skills | J36: SUSBINCO project | L36: Annika Ahlfors
A37: Kajaanin Ammattikorkeakoulu Oy | B37: 386089 | C37: Y | E37: Finland | F37: Finland | G37: N | H37: B | I37: Product, service or technology trainings | J37: Metsästä energiaksi - MENER project funding 2023, EMC-testing | L37: Susanna Glad
A38: Stichting Gasturbine Onderwijs | B38: 644372 | E38: Finland | G38: N | H38: B | I38: Product, service or technology trainings | J38: Turbomachinery course | L38: Sylvia Malenstein
A39: HAK Nova Oy | B39: 630977 | C39: Y | D39: 3000 | E39: Finland | F39: EMEA | G39: Y | H39: B | I39: Coaching and work counseling | J39: coaching | L39: Leila Figueiredo => Eero Halmari
A40: Imaction | B40: 646544 | C40: Y | E40: Finland | G40: N | H40: B | I40: Leadership, management and team development | J40: Forward through change training; https://www.imaction.fi/ | L40: Mari Poikonen
A41: Eeva Niskavaara Consulting Oy | B41: 402182 | C41: Y | E41: Finland | F41: Finland | G41: N | H41: B | I41: Interaction/ presentation/ communication/ influencing | J41: Finance trainings | L41: Bill Zervas => Reijo Heinämäki
A42: The European Institute of Purchasing Management | B42: 239503 | E42: Finland | G42: N | H42: B | I42: Various/other skills | J42: Participation EIPM Peter Kraljic Awards 2023 | L42: Jani Suomalainen
A43: Abitata | B43: 382766 | C43: Y | E43: Finland | F43: Finland | G43: N | H43: C | I43: Business culture and language training | J43: language training | L43: Tuomas Himanka
A44: BCFO Business Coaching Finland Oy | B44: 374821 | C44: Y | E44: Finland | F44: Finland | G44: N | H44: C | I44: Coaching and work counselling | J44: Leadership trainings, coaching, (Onnistuva johtaja -development process) | L44: Kimmo Pitkänen
A45: Berlitz Language Services | B45: 508657 | C45: Y | E45: Finland | F45: Global | G45: N | H45: C | I45: Business culture and language training | J45: German language training 30 lessons | L45: Jussi Ranta
A46: Eduhouse Oy | B46: 349909 | C46: Y | E46: Finland | G46: N | H46: C | I46: Elearnings and digital learning solutions | J46: Social media content creation using ChatGPT; "25.10.2023 Somen sisällöntuotanto ChatGPT:llä, osallistuja: Mirkka Aarti" | L46: Not found
A47: Elina Lillstrang Oy | B47: 637008 | C47: Y | E47: Finland | F47: Finland | G47: Y | H47: C | I47: Coaching and work counselling | J47: Logistics transformation journey, GFO Growth journey, other assignments | L47: Satu Pennanen
A48: Flow2Work Oy | B48: 662923 | E48: Finland | G48: N | H48: C | I48: Coaching and work counselling | J48: coaching & headhunting | L48: Outi Meroma
A49: Goethe Institut | B49: 602523 | C49: Y | E49: Finland | G49: N | H49: C | I49: Business culture and language training | J49: German language training | L49: Jouko Latva-Somppi
A50: GoodCo Oy | B50: 650488 | D50: 3500 | E50: Finland | G50: N | H50: C | I50: HSE, quality and work wellbeing | J50: Resilience as a resource webinar rights | K50: x | L50: Eeva Lapila
A51: Innotiimi Oy | B51: 604023 | C51: Y | D51: 2500 | E51: Finland | F51: EMEA / Global | G51: Y | H51: C | I51: HSE, quality and work wellbeing | J51: RCA training, work guidance | K51: x | L51: Tuija Korpela, Eero Halmari
A52: Koolituskorraldus OÜ | B52: 641406 | E52: Finland | G52: N | H52: C | I52: Business culture and language training | J52: Finnish language training | L52: Olli Koivumäki
A53: Ratekoulutus Oy | B53: 351748 | C53: Y | E53: Finland | G53: N | H53: C | I53: Elearnings and digital learning solutions | J53: Excel & ChatGPT training for Logistics: "Global Category Manager Jari Enberg, osallistuminen Excel ja ChatGPT: hyödynnä nyt tekoälyä työssäsi (3 h) 15.11.2023 Zoom Webinar" | L53: Not found
A54: Satakunnan Monikulttuuriyhdistys ry | B54: 646402 | C54: N | E54: Finland | F54: Finland | G54: N | H54: C | I54: Business culture and language training | J54: Finnish language training | L54: Juha Riihimäki
A55: Soutwestern Consulting LTD | B55: 656486 | C55: Y | E55: Finland | F55: Global | G55: N | H55: C | I55: Coaching and work counselling | J55: Coaching for sales | L55: Mari Joensuu
A56: Tresentio Oy | B56: 623745 | C56: Y | E56: Finland | F56: Finland | G56: N | H56: C | I56: Coaching and work counselling | J56: Coaching event | L56: Riikka Nurmi
A57: Työhyvinvointi Tienhaara Oy | B57: 664475 | C57: Y | E57: Finland | G57: N | H57: C | I57: HSE, quality and work wellbeing | J57: TYHY -event, worker well-being | K57: x | L57: Krista Laukkanen
A58: Viktor Wieser | B58: 657422 | E58: Finland | G58: N | H58: C | I58: Business culture and language training | J58: German language training | L58: Jari Juhani Manninen
A59: Y3 Milestone Coaching & Consulting Oy Ltd | B59: 617031 | C59: Y | E59: Finland | G59: N | H59: C | I59: Coaching and work counselling | J59: Coaching | L59: Not found
A60: Yrittäjien Koulutuskeskus Oy | B60: 607035 | C60: Y | E60: Finland | F60: Finland | G60: N | H60: C | I60: Various/other skills | J60: Customs training: Yritykesi tulliasiat kuntoon muuttuvassa maailmassa, Työnantajan velvoitteet työntekijän työkyvyn alentuessa | L60: Minna Talasaho
A61: Sähköinfo Oy | B61: 604917 | E61: Finland | G61: N | H61: C | I61: Product, service or technology trainings | J61: ST-online versions, SFS-handbook, electrical permits and qualification annual fee for database | K61: x | L61: Kari Leppänen
A62: Quality Knowhow Karjalainen Oy | B62: 607929 | C62: Y | E62: Finland | G62: N | H62: C | I62: HSE, quality and work wellbeing | J62: Minitab- annual user license 18 persons , Factory Physics training | K62: x | L62: Juuso Maskonen
A63: Finn-Tarkastus Oy | B63: 639705 | E63: Finland | G63: N | H63: C | I63: HSE, quality and work wellbeing | J63: Machine safety training | K63: x | L63: Ulla Ravattinen
A64: Laatukeskus Excellence Finland Oy | B64: 163473 | E64: Finland | G64: N | H64: C | I64: HSE, quality and work wellbeing | J64: ISO 9001 auditing training | K64: x | L64: Mika Granlund
A65: Pohto Oy | B65: 602473 | E65: Finland | G65: N | H65: C | I65: HSE, quality and work wellbeing | J65: Radiation safety office training | K65: x | L65: Reijo Heikura
A66: Suomen Ensiapukoulutus Oy | B66: 332750 | E66: Finland | G66: N | H66: C | I66: HSE, quality and work wellbeing | J66: Work safety, first aid, fire work safety | K66: x | L66: Sauli Seikkula
A67: Risknowlogy GmbH | B67: 304654 | E67: Finland | G67: N | H67: C | I67: HSE, quality and work wellbeing | J67: SIL Verification and calculation workshop, functional safety consulting | K67: x | L67: Marja-Liisa Ajo
A68: Länsirannikon Koulutus Oy | B68: 397858 | E68: Finland | G68: N | H68: C | I68: HSE, quality and work wellbeing | J68: HSE trainings | K68: x | L68: Toni Sairanen
A69: Tina Sammi Oy | B69: 633539 | E69: Finland | G69: N | H69: C | I69: HSE, quality and work wellbeing | J69: Trainings related to liquefied petroleum gas | K69: x | L69: Ulla-Maija Olkinuora
A70: KjV-Palvelut | B70: 633686 | E70: Finland | G70: N | H70: C | I70: HSE, quality and work wellbeing | J70: First aid training | K70: x | L70: Kari Rantama
A71: Sepon Konttori | B71: 384798 | E71: Finland | G71: N | H71: C | I71: HSE, quality and work wellbeing | J71: Radiation safety office training | K71: x | L71: Kari Rantama
A72: Punainen Risti Ensiapu Oy | B72: 408310 | E72: Finland | G72: N | H72: C | I72: HSE, quality and work wellbeing | J72: First aid training | K72: x | L72: Jussi Salonkari
A73: Safeguard Engineering Oy | B73: 656961 | E73: Finland | G73: N | H73: C | I73: HSE | J73: HSE - putoamissuojauskoulutus | K73: x | L73: Annina Salmi
A74: Tampereen Sammutin osakeyhtiö | B74: 637584 | E74: Finland | G74: N | H74: C | I74: HSE, quality and work wellbeing | J74: Fire extinguisher inspection and new extinguishers | K74: x | L74: Mari Joensuu
A75: Tulityö ja työturvallisuuskoulutus Kalle Hankomäki Oy | B75: 380921 | E75: Finland | G75: N | H75: C | I75: HSE, quality and work wellbeing | K75: x | L75: Matti J Saarinen
A76: Tietojärjestelmien Tarkastus Ja Valvonta Ry | B76: 168488 | E76: Finland | G76: N | H76: C | I76: HSE, quality and work wellbeing | J76: CISA-certification training | K76: x | L76: Jukka Ylijoki
A77: Opiks-Tiimi Oy | B77: 224444 | E77: Finland | G77: N | H77: C | I77: HSE, quality and work wellbeing | J77: EU machine directive training | K77: x | L77: Mikko Rautiainen
A78: Protektu Oy | B78: 650581 | E78: Finland | G78: N | H78: C | I78: HSE, quality and work wellbeing | J78: hot work training | K78: x | L78: Kari Rantama
A79: Työturvallisuuskeskus ry | B79: 603082 | E79: Finland | G79: N | H79: C | I79: HSE, quality and work wellbeing | K79: x | L79: Eero Määttä
A80: Ukkonen Palvelut Oy | B80: 628955 | E80: Finland | G80: N | H80: C | I80: HSE, quality and work wellbeing | J80: Hot work license | K80: x | L80: Kari Hytönen
A81: Logistiikka Koulutus V & P Ky | B81: 304456 | E81: Finland | G81: N | H81: C | I81: HSE, quality and work wellbeing | J81: Fire safety training | K81: x | L81: Vesa Huhtanen
A82: Innen Oy | B82: 401590 | E82: Finland | G82: N | H82: C | I82: HSE, quality and work wellbeing | J82: Fire extinguishing training | K82: x | L82: Juha Riihimäki
A83: Suomen Punainen Risti Varsinais-Suomen piiri | B83: 612001 | E83: Finland | G83: N | H83: C | I83: HSE, quality and work wellbeing | K83: x | L83: Tuomas Etula
A84: UTK-YHTIÖT OY | B84: 404140 | E84: Finland | G84: N | H84: C | I84: HSE, quality and work wellbeing | J84: Occupational safety card training | K84: x | L84: Niko Pietikäinen
A85: Uudenmaan Koulutuskeskus Oy | B85: 386100 | E85: Finland | G85: N | H85: C | I85: HSE, quality and work wellbeing | J85: Emergency first aid course, fire distinguishing course | K85: x | L85: Max Jansson
A86: Eduko koulutus- ja yrityspalvelut Oy | B86: 666645 | E86: Finland | G86: N | H86: C | I86: HSE, quality and work wellbeing | J86: Occupational safety card training | K86: x | L86: Toni Wathen
A87: Safety First | B87: 663583 | E87: Finland | G87: N | H87: C | I87: HSE, quality and work wellbeing | J87: Fire work safety training | K87: x | L87: Sonja Montonen
A88: Suomen Pelastusalan Keskusjärjestö | B88: 603777 | E88: Finland | G88: N | H88: C | I88: HSE, quality and work wellbeing | J88: Civil protection specialist training | K88: x | L88: Not found
A89: Länsi-Suomen työturvallisuuskoulutus Oy | B89: 332757 | E89: Finland | G89: N | H89: C | I89: HSE, quality and work wellbeing | K89: x | L89: Noomi Stenberg
A90: Koulutuspalvelu sahkot.fi | B90: 641539 | E90: Finland | G90: N | H90: C | I90: HSE, quality and work wellbeing | J90: Electric work safety course SFS 6002 | K90: x | L90: Marko Saarinen
A91: Primaonline Oy | B91: 641093 | E91: Finland | G91: N | H91: C | I91: HSE, quality and work wellbeing | J91: Electric work safety course SFS 6002 | K91: x | L91: Heidi Romppainen
A92: Allenatore | B92: 639270 | E92: Finland | G92: N | H92: C | I92: HSE, quality and work wellbeing | J92: Fire work safety training | K92: x | L92: Juho Särkijärvi
A93: TES-toimi Oy | B93: 380922 | E93: Finland | G93: N | H93: C | I93: HSE, quality and work wellbeing | J93: Emergency first aid training | K93: x | L93: Manu Kapiainen
A94: VAAOkoulutus Oy | B94: 404346 | E94: Finland | G94: N | H94: C | I94: HSE, quality and work wellbeing | K94: x | L94: Mika Uusitalo
A95: Koulutustiimi ViisiPäivää Ky | B95: 621769 | E95: Finland | G95: N | H95: C | I95: HSE, quality and work wellbeing | K95: x | L95: Ulla-Maija Olkinuora
A96: Anakom Oy | B96: 636419 | E96: Finland | G96: N | H96: C | I96: HSE, quality and work wellbeing | J96: Occupational safety card training | K96: x | L96: Juha Riihimäki
A97: Oljamikoti Oy | B97: 655289 | E97: Finland | G97: N | H97: C | I97: HSE, quality and work wellbeing | J97: Emergency first aid training | K97: x | L97: Nenna Järvinen
A98: Sec And Safe Solutions Oy | B98: 668449 | E98: Finland | G98: N | H98: C | I98: HSE, quality and work wellbeing | J98: Occupational safety card training | K98: x | L98: Nenna Järvinen
